Workbook
Name _PAG1: #REF!
Name _PAG1: #REF!
Name _PAG1: #REF!
Name _PAG3: #REF!
Name _PAG3: #REF!
Name _PAG4: #REF!
Name _PAG5: #REF!
Name _PAG6: #REF!
Name \P: #REF!
Name \W: #REF!
Name \Z: #REF!
Name CONC: #REF!
Name CONC: #REF!
Name conc1: #REF!
Name CuNuevo_ConPelaCama_tmf: [1]FUNDICIÓN!$P$73
Name CuNuevo_ConPelaCama_tmf: [1]FUNDICIÓN!$P$73
Name CuNuevo_ConPelaCama_tms: [1]FUNDICIÓN!$O$73
Name CuNuevo_ConPelaCama_tms: [1]FUNDICIÓN!$O$73
Name ECL_DelBal_por: 'Resumen Planta Pellets'!$H$37
Name ECL_DelBal_tmf: 'Resumen Planta Pellets'!$F$37
Name FEED: #REF!
Name FEED: #REF!
Name feed1: #REF!
Name GCONC: #REF!
Name GCONC: #REF!
Name GFEED: #REF!
Name GFEED: #REF!
Name GTAIL: #REF!
Name INVROLL: #REF!
Name MENU: #REF!
Name Month: #REF!
Name PP: [1]FUNDICIÓN!$P$73
Name solver_adj: 'Bal Los Colorados'!$M$46:$N$69
Name solver_adj: 'Resumen Planta Pellets'!$P$10
Name solver_adj: Utilidad!$N$67:$O$126
Name solver_cvg: 0.0001
Name solver_cvg: 0.0001
Name solver_cvg: 0.0001
Name solver_cvg: 0.0001
Name solver_drv: 1
Name solver_drv: 2
Name solver_drv: 1
Name solver_drv: 1
Name solver_eng: 1
Name solver_eng: 1
Name solver_eng: 1
Name solver_eng: 1
Name solver_est: 1
Name solver_est: 1
Name solver_est: 1
Name solver_est: 1
Name solver_itr: 2147483647
Name solver_itr: 2147483647
Name solver_itr: 2147483647
Name solver_itr: 2147483647
Name solver_lhs1: 'Bal Los Colorados'!$AB$45
Name solver_lhs1: Utilidad!$AB$67:$AB$90
Name solver_lhs10: 'Bal Los Colorados'!$AB$54
Name solver_lhs10: Utilidad!$U$68
Name solver_lhs11: 'Bal Los Colorados'!$AB$55

Sheet Resumen Planta Pellets
F2: BALANCE METALÚRGICO - VALLE HUASCO
F4: REPORTE DE PLANTA DE PELLETS | M4: FECHA DE BALANCE | P4: =+Diagrama!C4 -> 45386
G7: TONELAJE | H7: TONELAJE | I7: LEY | J7: FINO | N7: TONELAJE | O7: TONELAJE | P7: LEY | Q7: FINO
G8: TMH | H8: TMS | I8: % FeT | J8: TMF | N8: TMH | O8: TMS | P8: % FeT | Q8: TMF
D9: ENTRADAS | K9: PRODUCCIÓN
C10: FL_218_501_01 | D10: Preconcentrado hacia Molinos | G10: =+Diagrama!AI12 -> 231594.14 | H10: =+Diagrama!I25 -> 229834.02 | I10: =+Diagrama!I26 -> 0.60589335 | J10: =I10*H10 -> 139254.91 | K10: Pellet Feed | N10: =+Diagrama!J72 -> 209647.65 | O10: =+Diagrama!H46 -> 192143 | P10: =+Diagrama!H47 -> 0.6865 | Q10: =P10*O10 -> 131906.17
D11: Finos hacia Molinos | G11: 0 | H11: 0 | I11: 0 | J11: =I11*H11 -> 0 | K11: Pellet Producto | N11: =+Diagrama!J70 -> 0 | O11: =+Diagrama!P49 -> 0 | P11: =+Diagrama!P50 -> 0 | Q11: =P11*O11 -> 0
D12: Pellet Producto desde Pila Emergencia | G12: 0 | H12: 0 | I12: 0 | J12: 0 | K12: Pellet Chips | N12: =+Diagrama!J71 -> 0 | O12: =+Diagrama!R36 -> 0 | P12: =+Diagrama!R37 -> 0 | Q12: =P12*O12 -> 0
D13: Pellet Chips desde Pila Emergencia | G13: 0 | H13: 0 | I13: 0 | J13: 0 | K13: Sinter Feed hacia Planta de Pellets | N13: =+Diagrama!J77 -> 164651.14 | O13: =+Diagrama!J77*(1-Diagrama!AE7) -> 163082 | P13: =+Diagrama!H5 -> 0.6339236 | Q13: =P13*O13 -> 103381.53
C14: FL_000_501_03 | K14: Finos Hematíticos | N14: =+Diagrama!J78 -> 2203 | O14: =+Diagrama!J78*(1-Diagrama!AE32) -> 2141.316 | P14: ='Datos Extra'!E24 -> 0.6256 | Q14: =P14*O14 -> 1339.6073
D15: TOTAL | G15: =SUM(G10:G14) -> 231594.14 | H15: =SUM(H10:H14) -> 229834.02 | I15: =I10 -> 0.60589335 | J15: =J10 -> 139254.91 | K15: TOTAL | N15: =SUM(N10:N14) -> 376501.79 | O15: =SUM(O10:O14) -> 357366.32 | P15: =+Q15/O15 -> 0.66214216 | Q15: =SUM(Q10:Q14) -> 236627.3
D16: EMBARQUES | K16: PÉRDIDAS
D17: Sinter Feed | G17: =+Diagrama!K77 -> 204999.49 | H17: =+Diagrama!N4 -> 202642 | I17: =+Diagrama!N5 -> 0.63386388 | J17: =I17*H17 -> 128447.44 | K17: DRF | N17: - | O17: =+Diagrama!D28 -> 20480.4 | P17: =+Diagrama!D29 -> 0.105183 | Q17: =P17*O17 -> 2154.1899
D18: Pellet Feed | G18: =+Diagrama!K72 -> 112763.79 | H18: =+G18*(1-Diagrama!AE19) -> 103878 | I18: =+Diagrama!C42 -> 0.6868 | J18: =I18*H18 -> 71343.41 | K18: TOTAL | N18: =N17 -> - | O18: =O17 -> 20480.4 | P18: =P17 -> 0.105183 | Q18: =P18*O18 -> 2154.1899
D19: Pellet Producto | G19: =+Diagrama!K70 -> 0 | H19: =+Diagrama!M52 -> 0 | I19: =+Diagrama!M53 -> 0 | J19: =I19*H19 -> 0
D20: Finos Huasco | G20: 0 | H20: =Diagrama!K78*(1-'Datos Extra'!D28) -> 0 | I20: =+Diagrama!T34 -> 0 | J20: =I20*H20 -> 0
D21: Pellet Chips | G21: =+Diagrama!K71 -> 66000 | H21: =IF(G21=0,0,G21*(1-Diagrama!AE26)) -> 66000 | I21: =IF(G21=0,0,Diagrama!AG26) -> 0 | J21: =I21*H21 -> 0
D22: TOTAL | G22: =SUM(G17:G21) -> 383763.28 | H22: =SUM(H17:H21) -> 372520 | I22: =SUMPRODUCT(H17:H21,I17:I21)/H22 -> 0.53632249 | J22: =SUM(J17:J21) -> 199790.85
D23: INVENTARIOS | H23: TMS | I23: % FeT | J23: TMF | K23: SAP | L23: DIF
D24: Preconcentrado en Cancha | O24: 0.76
D25: Finos Recuperados | O25: 8.68
D26: Sinter Feed en Cancha | O26: 0.76
D27: Pellet Feed en Cancha | O27: 8.39
D28: Finos Huasco en Cancha
D29: Pellet Producto en Cancha | O29: 0.05
D30: Pellet Chip en Cancha | O30: 0.05
D31: TOTAL | H31: 0 | J31: 0 | K31: 0 | L31: 0
D33: INDICADORES VALLE HUASCO
D35: RECUPERACIÓN EN PESO | K35: RECUPERACIÓN METALÚRGICA
D36: =Diagrama!O19 -> 0.82684451 | K36: =Diagrama!O21 -> 0.93684598

Sheet Bal Los Colorados
J2: 1 | K2: 2 | L2: 3 | M2: 4 | N2: 5 | O2: 6 | P2: 7 | Q2: 8 | S2: 9 | T2: 10
J3: Acopio Mina | K3: Nodo Alim Mina CH | L3: CH Mina | M3: Stock Prec Los Colorados | N3: Stock Grueso CH | O3: Concentracc. Mag Los Colorados | P3: Nodo Separador Producto Conc Mag | Q3: Stock Rechazo | R3: Nodo Alim Planta Rechazo | S3: Planta Rechazos | T3: Stock P40 | W3: {=+TRANSPOSE(I3:T27)} -> 0
G4: I | H4: 1 | I4: Alimentación Mina | J4: 0 | K4: 1 | L4: 0 | M4: 0 | N4: 0 | O4: 0 | P4: 0 | Q4: 0 | R4: 0 | S4: 0 | T4: 0 | X4: 0 | Y4: -1 | Z4: -1 | AB4: 0 | AC4: 0 | AD4: 0 | AE4: 0 | AF4: 0 | AG4: 1 | AH4: 0 | AI4: 0 | AJ4: 0 | AK4: 0 | AL4: 0 | AM4: 0 | AN4: 0 | AO4: 0 | AP4: 0 | AQ4: 0 | AR4: 0 | AS4: 0 | AT4: 0 | AU4: 0
G5: I | H5: 2 | I5: Alim a Planta desde Acopio Mina | J5: -1 | K5: 1 | L5: 0 | M5: 0 | N5: 0 | O5: 0 | P5: 0 | Q5: 0 | R5: 0 | S5: 0 | T5: 0 | X5: 1 | Y5: 1 | Z5: 0 | AA5: 0 | AB5: -1 | AC5: 0 | AD5: 0 | AE5: 0 | AF5: 0 | AG5: 0 | AH5: 0 | AI5: 0 | AJ5: 0 | AK5: 0 | AL5: 0 | AM5: 0 | AN5: 0 | AO5: 0 | AP5: 0 | AQ5: 0 | AR5: 0 | AS5: 0 | AT5: 0 | AU5: 0
G6: I | H6: 3 | I6: Acopio Mina a Terceros | J6: -1 | K6: 0 | L6: 0 | M6: 0 | N6: 0 | O6: 0 | P6: 0 | Q6: 0 | R6: 0 | S6: 0 | T6: 0 | X6: 0 | Y6: 0 | Z6: 0 | AA6: 0 | AB6: 1 | AC6: -1 | AD6: -1 | AE6: 0 | AF6: 0 | AG6: 0 | AH6: 0 | AI6: 0 | AJ6: 0 | AK6: 0 | AL6: 0 | AM6: 0 | AN6: 0 | AO6: 0 | AP6: 0 | AQ6: 0 | AR6: 0 | AS6: 0 | AT6: 0 | AU6: 0
G7: I | H7: 4 | I7: Delta S Acopio Mina | J7: =+#REF! -> #REF! | K7: 0 | L7: 0 | M7: 0 | N7: 0 | O7: 0 | P7: 0 | Q7: 0 | R7: 0 | S7: 0 | T7: 0 | X7: 0 | Y7: 0 | Z7: 0 | AA7: 0 | AB7: 0 | AC7: 1 | AD7: 0 | AE7: 0 | AF7: 0 | AG7: -1 | AI7: -1 | AJ7: 1 | AK7: 0 | AL7: 0 | AM7: 0 | AN7: 0 | AO7: 0 | AP7: 0 | AQ7: 0 | AR7: 0 | AS7: 0 | AT7: 0 | AU7: -1
G8: I | H8: 5 | I8: Alim a Chancado | J8: 0 | K8: -1 | L8: 1 | M8: 0 | N8: 0 | O8: 0 | P8: 0 | Q8: 0 | R8: 0 | S8: 0 | T8: 0 | X8: 0 | Y8: 0 | Z8: 0 | AA8: 0 | AB8: 0 | AC8: 0 | AD8: 1 | AF8: -1 | AG8: 0 | AH8: 0 | AI8: 0 | AJ8: 0 | AK8: 0 | AL8: 0 | AM8: 0 | AN8: 0 | AO8: 0 | AP8: 0 | AQ8: 0 | AR8: 0 | AS8: 0 | AT8: 0 | AU8: 0
G9: I | H9: 6 | I9: Chanc a Stock Prec Los Col. | J9: 0 | K9: 0 | L9: -1 | M9: 1 | N9: 0 | O9: 0 | P9: 0 | Q9: 0 | R9: 0 | S9: 0 | T9: 0 | X9: 0 | Y9: 0 | Z9: 0 | AA9: 0 | AB9: 0 | AC9: 0 | AD9: 0 | AE9: 0 | AF9: 1 | AG9: 0 | AH9: 0 | AI9: 0 | AJ9: -1 | AK9: -1 | AL9: 0 | AM9: 0 | AN9: 0 | AO9: 0 | AP9: 0 | AQ9: 0 | AR9: 0 | AS9: 0 | AT9: 0 | AU9: 0
G10: I | H10: 7 | I10: Chanc a Stock Grueso | J10: 0 | K10: 0 | L10: -1 | M10: 0 | N10: 1 | O10: 0 | P10: 0 | Q10: 0 | R10: 0 | S10: 0 | T10: 0 | X10: 0 | Y10: 0 | Z10: 0 | AA10: 0 | AB10: 0 | AC10: 0 | AD10: 0 | AE10: 0 | AF10: 0 | AG10: 0 | AH10: 0 | AI10: 0 | AJ10: 0 | AK10: 1 | AL10: -1 | AM10: -1 | AN10: 0 | AO10: 0 | AP10: 0 | AQ10: 0 | AR10: 0 | AS10: 0 | AT10: 0 | AU10: 0
G11: I | H11: 8 | I11: Delta Stock de Grueso | J11: 0 | K11: 0 | L11: 0 | M11: 0 | N11: =+#REF! -> #REF! | O11: 0 | P11: 0 | Q11: 0 | R11: 0 | S11: 0 | T11: 0 | X11: 0 | Y11: 0 | Z11: 0 | AA11: 0 | AB11: 0 | AC11: 0 | AD11: 0 | AE11: 0 | AF11: 0 | AG11: 0 | AH11: 0 | AI11: 0 | AJ11: 0 | AK11: 0 | AL11: 1 | AM11: 0 | AO11: -1 | AP11: 0 | AQ11: 0 | AR11: 0 | AS11: 0 | AT11: 0 | AU11: 0
G12: I | H12: 9 | I12: De Stock Grueso a conc magn (alim A52 y A82) | J12: 0 | K12: 0 | L12: 0 | M12: 0 | N12: -1 | O12: 1 | P12: 0 | Q12: 0 | R12: 0 | S12: 0 | T12: 0 | X12: 0 | Y12: 0 | Z12: 0 | AA12: 0 | AB12: 0 | AC12: 0 | AD12: 0 | AE12: 0 | AF12: 0 | AG12: 0 | AH12: 0 | AI12: 0 | AJ12: 0 | AK12: 0 | AL12: 0 | AM12: 1 | AN12: 0 | AO12: 1 | AP12: -1 | AQ12: 0 | AR12: 0 | AS12: 0 | AT12: 0 | AU12: 0
G13: I | H13: 10 | I13: Stock Prec a (o desde) Acopio Mina | J13: 1 | K13: 0 | L13: 0 | M13: -1 | N13: 0 | O13: 0 | P13: 0 | Q13: 0 | R13: 0 | S13: 0 | T13: 0 | X13: 0 | Y13: 0 | Z13: 0 | AA13: 0 | AB13: 0 | AC13: 0 | AD13: 0 | AE13: 0 | AF13: 0 | AG13: 0 | AH13: 0 | AI13: 0 | AJ13: 0 | AK13: 0 | AL13: 0 | AM13: 0 | AN13: 0 | AO13: 0 | AP13: 1 | AQ13: -1 | AR13: -1 | AS13: 0 | AT13: 0 | AU13: 0
G14: I | H14: 11 | I14: Delta Stock Prec | J14: 0 | K14: 0 | L14: 0 | M14: =+#REF! -> #REF! | N14: 0 | O14: 0 | P14: 0 | Q14: 0 | R14: 0 | S14: 0 | T14: 0 | X14: 0 | Y14: 0 | Z14: 0 | AA14: 0 | AB14: 0 | AC14: 0 | AD14: 0 | AE14: 0 | AF14: 0 | AG14: 0 | AH14: 0 | AI14: 0 | AJ14: 0 | AK14: 0 | AL14: 0 | AM14: 0 | AN14: 0 | AO14: 0 | AP14: 0 | AQ14: 0 | AR14: 1 | AT14: -1 | AU14: 0
G15: I | H15: 12 | I15: de Stock Prec a Terceros (a otras faenas) | J15: 0 | K15: 0 | L15: 0 | M15: -1 | N15: 0 | O15: 0 | P15: 0 | Q15: 0 | R15: 0 | S15: 0 | T15: 0
G16: I | H16: 13 | I16: de Conc Magnética a Stock Prec (Prod A52 y A 82) | J16: 0 | K16: 0 | L16: 0 | M16: 1 | N16: 0 | O16: -1 | P16: 0 | Q16: 0 | R16: 0 | S16: 0 | T16: 0
G17: I | H17: 14 | I17: total de rechazo | J17: 0 | K17: 0 | L17: 0 | M17: 0 | N17: 0 | O17: -1 | P17: 1 | Q17: 0 | R17: 0 | S17: 0 | T17: 0
G18: I | H18: 15 | I18: Rechazo a Stock de Rechazo | J18: 0 | K18: 0 | L18: 0 | M18: 0 | N18: 0 | O18: 0 | P18: -1 | Q18: 1 | R18: 0 | S18: 0 | T18: 0 | AG18: TMS | AH18: TMF
G19: I | H19: 16 | I19: alim fresca a Planta Rechazo | J19: 0 | K19: 0 | L19: 0 | M19: 0 | N19: 0 | O19: 0 | P19: -1 | Q19: 0 | R19: 1 | S19: 0 | T19: 0 | AF19: 1 | AG19: =+M46 -> 502781.82 | AH19: =+O46 -> 231983.79
G20: I | H20: 17 | I20: Delta Stock de Rechazo | J20: 0 | K20: 0 | L20: 0 | M20: 0 | N20: 0 | O20: 0 | P20: 0 | Q20: =+#REF! -> #REF! | R20: 0 | S20: 0 | T20: 0 | AF20: 2 | AG20: =+M47 -> 0 | AH20: =+O47 -> 0
G21: I | H21: 18 | I21: Stock Rechazo a Planta Rechazo | J21: 0 | K21: 0 | L21: 0 | M21: 0 | N21: 0 | O21: 0 | P21: 0 | Q21: -1 | R21: 1 | S21: 0 | T21: 0 | AF21: 3 | AG21: =+M48 -> 12961.629 | AH21: =+O48 -> 7704.8211
G22: I | H22: 19 | I22: Alimentación Planta Rechazo | J22: 0 | K22: 0 | L22: 0 | M22: 0 | N22: 0 | O22: 0 | P22: 0 | Q22: 0 | R22: -1 | S22: 1 | T22: 0 | AF22: 4 | AG22: =+M49 -> 1770.5762 | AH22: =+O49 -> 1150.0816
G23: I | H23: 20 | I23: Rechazo Final Los Colorados | J23: 0 | K23: 0 | L23: 0 | M23: 0 | N23: 0 | O23: 0 | P23: 0 | Q23: 0 | R23: 0 | S23: -1 | T23: 0 | AF23: 5 | AG23: =+M50 -> 502781.82 | AH23: =+O50 -> 231983.79
G24: I | H24: 21 | I24: Producción Planta Rechazo a Stock P40 | J24: 0 | K24: 0 | L24: 0 | M24: 0 | N24: 0 | O24: 0 | P24: 0 | Q24: 0 | R24: 0 | S24: -1 | T24: 1 | AF24: 6 | AG24: =+M51 -> 0 | AH24: =+O51 -> 0
G25: I | H25: 22 | I25: Delta Stock P40 | J25: 0 | K25: 0 | L25: 0 | M25: 0 | N25: 0 | O25: 0 | P25: 0 | Q25: 0 | R25: 0 | S25: 0 | T25: =+#REF! -> #REF! | AF25: 7 | AG25: =+M52 -> 502781.82 | AH25: =+O52 -> 231983.79
G26: I | H26: 23 | I26: Venta desde P40 | J26: 0 | K26: 0 | L26: 0 | M26: 0 | N26: 0 | O26: 0 | P26: 0 | Q26: 0 | R26: 0 | S26: 0 | T26: -1 | AF26: 8 | AG26: =+M53 -> 44584.89 | AH26: =+O53 -> 15862.289
G27: I | H27: 24 | I27: de Stoc Prec a Nodo Alim Planta de Pellet | J27: 0 | K27: 0 | L27: 0 | M27: -1 | N27: 0 | O27: 0 | P27: 0 | Q27: 0 | R27: 0 | S27: 0 | T27: 0 | AF27: 9 | AG27: =+M54 -> 458196.93 | AH27: =+O54 -> 216121.5
AF28: 10 | AG28: =+M55 -> 14732.205 | AH28: =+O55 -> 8854.9026
AF29: 11 | AG29: =+M56 -> 30901.955 | AH29: =+O56 -> 28476.531
AF30: 12 | AG30: =+M57 -> 16162.331 | AH30: =+O57 -> 9675.4587
AF31: 13 | AG31: =+M58 -> 345267.34 | AH31: =+O58 -> 198183.76
AF32: 14 | AG32: =+M59 -> 112929.59 | AH32: =+O59 -> 17937.737
AF33: 15 | AG33: =+M60 -> 30174.414 | AH33: =+O60 -> 5989.7466
AF34: 16 | AG34: =+M61 -> 82755.179 | AH34: =+O61 -> 11947.99
AF35: 17 | AG35: =+M62 -> 14174.322 | AH35: =+O62 -> 3614.2837
AF36: 18 | AG36: =+M63 -> 44348.737 | AH36: =+O63 -> 9604.0304
AF37: 19 | AG37: =+M64 -> 127103.92 | AH37: =+O64 -> 21552.02
AF38: 20 | AG38: =+M65 -> 108284.66 | AH38: =+O65 -> 14049.347
AF39: 21 | AG39: =+M66 -> 18819.257 | AH39: =+O66 -> 7502.6732
... AF42: 24 | AG42: =+M69 -> 673884.94 | AH42: =+O69 -> 410848.96
AB43: Balance de Nodos
J44: Valor Inicial | M44: Valores Calculados | R44: % cambio relativo r/ valores medidos | T44: Max Var Ton | V44: Max Var Ley | AB44: TMS | AC44: TMF | AE44: =+V45 -> #REF!
J45: TMS | K45: %FeT | M45: TMS | N45: %FeT | O45: TMF Fe | R45: TMS | S45: %Fe T | T45: =+MAX(T46:T69) -> #REF! | V45: =+MAX(V46:V69) -> #REF! | AA45: Acopio Mina | AB45: {=+MMULT(X4:AU14,AG19:AH42)} -> #VALUE!
H46: =+H4 -> 1 | I46: =+I4 -> Alimentación Mina | J46: =+#REF! -> #REF! | K46: =+#REF! -> #REF! | L46: E | M46: 502781.82 | N46: 0.46140051 | O46: =+M46*N46 -> 231983.79 | R46: =+IF(J46<>0,(M46-J46)/J46,0) -> #REF! | S46: =+IF(K46<>0,(N46-K46)/K46,0) -> #REF! | T46: =+IF(R46<>"",ABS(R46),0) -> #REF! | V46: =+IF(S46<>"",ABS(S46),0) -> #REF! | W46: 0.02 | AA46: Nodo Alim Mina CH
H47: =+H5 -> 2 | I47: =+I5 -> Alim a Planta desde Acopio Mina | J47: =+#REF! -> #REF! | K47: =+#REF! -> #REF! | M47: 0 | N47: 0 | O47: =+M47*N47 -> 0 | R47: =+IF(J47<>0,(M47-J47)/J47,0) -> #REF! | S47: =+IF(K47<>0,(N47-K47)/K47,0) -> #REF! | T47: =+IF(R47<>"",ABS(R47),0) -> #REF! | V47: =+IF(S47<>"",ABS(S47),0) -> #REF! | AA47: CH Mina
D48: Delta (FINAL - INI) | E48: ABS | F48: %FeT | H48: =+H6 -> 3 | I48: =+I6 -> Acopio Mina a Terceros | J48: =+#REF! -> #REF! | K48: =+#REF! -> #REF! | M48: 12961.629 | N48: 0.59443308 | O48: =+M48*N48 -> 7704.8211 | R48: =+IF(J48<>0,(M48-J48)/J48,0) -> #REF! | S48: =+IF(K48<>0,(N48-K48)/K48,0) -> #REF! | T48: =+IF(R48<>"",ABS(R48),0) -> #REF! | U48: 0 | V48: =+IF(S48<>"",ABS(S48),0) -> #REF! | AA48: Stock Prec Los Colorados
D49: =+#REF! -> #REF! | E49: =+#REF! -> #REF! | F49: =+#REF! -> #REF! | G49: =+IF(D49>0,1,IF(D49<>0,-1,0)) -> #REF! | H49: =+H7 -> 4 | I49: =+I7 -> Delta S Acopio Mina | J49: =+E49 -> #REF! | K49: =+F49 -> #REF! | L49: Inv | M49: 1770.5762 | N49: 0.64955214 | O49: =+M49*N49 -> 1150.0816 | P49: =+#REF! -> #REF! | Q49: =+M49-J49 -> #REF! | R49: =+IF(J49<>0,(M49-J49)/J49,0) -> #REF! | S49: =+IF(K49<>0,(N49-K49)/K49,0) -> #REF! | T49: =+IF(R49<>"",ABS(R49),0) -> #REF! | V49: =+IF(S49<>"",ABS(S49),0) -> #REF! | AA49: Stock Grueso CH
H50: =+H8 -> 5 | I50: =+I8 -> Alim a Chancado | J50: =+J46+J47 -> #REF! | K50: =+(J46*K46+J47*K47)/J50 -> #REF! | M50: 502781.82 | N50: 0.46140051 | O50: =+M50*N50 -> 231983.79 | R50: =+IF(J50<>0,(M50-J50)/J50,0) -> #REF! | S50: =+IF(K50<>0,(N50-K50)/K50,0) -> #REF! | T50: =+IF(R50<>"",ABS(R50),0) -> #REF! | V50: =+IF(S50<>"",ABS(S50),0) -> #REF! | AA50: Concentracc. Mag Los Colorados
H51: =+H9 -> 6 | I51: =+I9 -> Chanc a Stock Prec Los Col. | J51: 0 | K51: =+IF(J51<>0,(J50*K50-J52*K52)/J51,0) -> 0 | M51: 0 | N51: 0 | O51: =+M51*N51 -> 0 | R51: =+IF(J51<>0,(M51-J51)/J51,0) -> 0 | S51: =+IF(K51<>0,(N51-K51)/K51,0) -> 0 | T51: =+IF(R51<>"",ABS(R51),0) -> 0 | V51: =+IF(S51<>"",ABS(S51),0) -> 0 | AA51: Nodo Separador Producto Conc Mag
H52: =+H10 -> 7 | I52: =+I10 -> Chanc a Stock Grueso | J52: =+J50 -> #REF! | K52: =+K50 -> #REF! | M52: 502781.82 | N52: 0.46140051 | O52: =+M52*N52 -> 231983.79 | R52: =+IF(J52<>0,(M52-J52)/J52,0) -> #REF! | S52: =+IF(K52<>0,(N52-K52)/K52,0) -> #REF! | T52: =+IF(R52<>"",ABS(R52),0) -> #REF! | V52: =+IF(S52<>"",ABS(S52),0) -> #REF! | AA52: Stock Rechazo
D53: =+#REF! -> #REF! | E53: =+#REF! -> #REF! | F53: =+#REF! -> #REF! | G53: =+IF(D53>0,1,IF(D53<>0,-1,0)) -> #REF! | H53: =+H11 -> 8 | I53: =+I11 -> Delta Stock de Grueso | J53: =+E53 -> #REF! | K53: =+IF(J53<>0,F53,0) -> #REF! | L53: Inv | M53: 44584.89 | N53: 0.35577723 | O53: =+M53*N53 -> 15862.289 | P53: =+#REF! -> #REF! | Q53: =+M53-J53 -> #REF! | R53: =+IF(J53<>0,(M53-J53)/J53,0) -> #REF! | S53: =+IF(K53<>0,(N53-K53)/K53,0) -> #REF! | T53: =+IF(R53<>"",ABS(R53),0) -> #REF! | U53: 0.1 | V53: =+IF(S53<>"",ABS(S53),0) -> #REF! | AA53: Nodo Alim Planta Rechazo
H54: =+H12 -> 9 | I54: =+I12 -> De Stock Grueso a conc magn (alim A52 y A82) | J54: =+#REF! -> #REF! | K54: =+#REF! -> #REF! | M54: 458196.93 | N54: 0.47167819 | O54: =+M54*N54 -> 216121.5 | R54: =+IF(J54<>0,(M54-J54)/J54,0) -> #REF! | S54: =+IF(K54<>0,(N54-K54)/K54,0) -> #REF! | T54: =+IF(R54<>"",ABS(R54),0) -> #REF! | V54: =+IF(S54<>"",ABS(S54),0) -> #REF! | AA54: Planta Rechazos
H55: =+H13 -> 10 | I55: =+I13 -> Stock Prec a (o desde) Acopio Mina | J55: =+#REF! -> #REF! | K55: =+#REF! -> #REF! | M55: 14732.205 | N55: 0.60105751 | O55: =+M55*N55 -> 8854.9026 | R55: =+IF(J55<>0,(M55-J55)/J55,0) -> #REF! | S55: =+IF(K55<>0,(N55-K55)/K55,0) -> #REF! | T55: =+IF(R55<>"",ABS(R55),0) -> #REF! | U55: 0 | V55: =+IF(S55<>"",ABS(S55),0) -> #REF! | W55: 0.05 | AA55: Stock P40
D56: =+J58+J51-J69-J57-J55 -> #REF! | E56: =+#REF! -> #REF! | F56: =+(J58*K58+J51*K51-J69*K69-J57*K57-J55*K55)/(J58+J51-J69-J57-J55) -> #REF! | G56: =+IF(D56>0,1,IF(D56<>0,-1,0)) -> #REF! | H56: =+H14 -> 11 | I56: =+I14 -> Delta Stock Prec | J56: =+E56 -> #REF! | K56: =+F56 -> #REF! | L56: Inv | M56: 30901.955 | N56: 0.9215123 | O56: =+M56*N56 -> 28476.531 | P56: =+#REF! -> #REF! | Q56: =+M56-J56 -> #REF! | R56: =+IF(J56<>0,(M56-J56)/J56,0) -> #REF! | S56: =+IF(K56<>0,(N56-K56)/K56,0) -> #REF! | T56: =+IF(R56<>"",ABS(R56),0) -> #REF! | V56: =+IF(S56<>"",ABS(S56),0) -> #REF!
H57: =+H15 -> 12 | I57: =+I15 -> de Stock Prec a Terceros (a otras faenas) | J57: =+#REF! -> #REF! | K57: =+#REF! -> #REF! | L57: Venta | M57: 16162.331 | N57: 0.59864253 | O57: =+M57*N57 -> 9675.4587 | R57: =+IF(J57<>0,(M57-J57)/J57,0) -> #REF! | S57: =+IF(K57<>0,(N57-K57)/K57,0) -> #REF! | T57: =+IF(R57<>"",ABS(R57),0) -> #REF! | U57: 0 | V57: =+IF(S57<>"",ABS(S57),0) -> #REF! | W57: 0.01 | AA57: suma | AB57: =+SUM(ANCHORARRAY(AB45)) -> #NAME?
H58: =+H16 -> 13 | I58: =+I16 -> de Conc Magnética a Stock Prec (Prod A52 y A 82) | J58: =+#REF! -> #REF! | K58: =+#REF! -> #REF! | M58: 345267.34 | N58: 0.5740009 | O58: =+M58*N58 -> 198183.76 | R58: =+IF(J58<>0,(M58-J58)/J58,0) -> #REF! | S58: =+IF(K58<>0,(N58-K58)/K58,0) -> #REF! | T58: =+IF(R58<>"",ABS(R58),0) -> #REF! | U58: 0.03 | V58: =+IF(S58<>"",ABS(S58),0) -> #REF! | AA58: Func Obj | AB58: =+SUM(J100:K123) -> #REF!
H59: =+H17 -> 14 | I59: =+I17 -> total de rechazo | J59: =+J60+J61 -> #REF! | K59: =+K60 -> #REF! | M59: 112929.59 | N59: 0.15884 | O59: =+M59*N59 -> 17937.737 | R59: =+IF(J59<>0,(M59-J59)/J59,0) -> #REF! | S59: =+IF(K59<>0,(N59-K59)/K59,0) -> #REF! | T59: =+IF(R59<>"",ABS(R59),0) -> #REF! | U59: 0.02 | V59: =+IF(S59<>"",ABS(S59),0) -> #REF! | W59: 0.05
H60: =+H18 -> 15 | I60: =+I18 -> Rechazo a Stock de Rechazo | J60: =+#REF! -> #REF! | K60: =+#REF! -> #REF! | M60: 30174.414 | N60: 0.19850416 | O60: =+M60*N60 -> 5989.7466 | R60: =+IF(J60<>0,(M60-J60)/J60,0) -> #REF! | S60: =+IF(K60<>0,(N60-K60)/K60,0) -> #REF! | T60: =+IF(R60<>"",ABS(R60),0) -> #REF! | V60: =+IF(S60<>"",ABS(S60),0) -> #REF!
H61: =+H19 -> 16 | I61: =+I19 -> alim fresca a Planta Rechazo | J61: =+#REF! -> #REF! | K61: =+#REF! -> #REF! | M61: 82755.179 | N61: 0.14437755 | O61: =+M61*N61 -> 11947.99 | R61: =+IF(J61<>0,(M61-J61)/J61,0) -> #REF! | S61: =+IF(K61<>0,(N61-K61)/K61,0) -> #REF! | T61: =+IF(R61<>"",ABS(R61),0) -> #REF! | V61: =+IF(S61<>"",ABS(S61),0) -> #REF!
D62: =+#REF! -> #REF! | E62: =+ABS(D62) -> #REF! | F62: =+#REF! -> #REF! | G62: =+IF(D62>0,1,IF(D62<>0,-1,0)) -> #REF! | H62: =+H20 -> 17 | I62: =+I20 -> Delta Stock de Rechazo | J62: =+E62 -> #REF! | K62: =+F62 -> #REF! | L62: Inv | M62: 14174.322 | N62: 0.25498811 | O62: =+M62*N62 -> 3614.2837 | P62: =+#REF! -> #REF! | Q62: =+M62-J62 -> #REF! | R62: =+IF(J62<>0,(M62-J62)/J62,0) -> #REF! | S62: =+IF(K62<>0,(N62-K62)/K62,0) -> #REF! | T62: =+IF(R62<>"",ABS(R62),0) -> #REF! | V62: =+IF(S62<>"",ABS(S62),0) -> #REF!
H63: =+H21 -> 18 | I63: =+I21 -> Stock Rechazo a Planta Rechazo | J63: =+#REF! -> #REF! | K63: =+#REF! -> #REF! | M63: 44348.737 | N63: 0.21655702 | O63: =+M63*N63 -> 9604.0304 | R63: =+IF(J63<>0,(M63-J63)/J63,0) -> #REF! | S63: =+IF(K63<>0,(N63-K63)/K63,0) -> #REF! | T63: =+IF(R63<>"",ABS(R63),0) -> #REF! | V63: =+IF(S63<>"",ABS(S63),0) -> #REF! | W63: 0.03
H64: =+H22 -> 19 | I64: =+I22 -> Alimentación Planta Rechazo | J64: =+#REF! -> #REF! | K64: =+#REF! -> #REF! | M64: 127103.92 | N64: 0.16956221 | O64: =+M64*N64 -> 21552.02 | R64: =+IF(J64<>0,(M64-J64)/J64,0) -> #REF! | S64: =+IF(K64<>0,(N64-K64)/K64,0) -> #REF! | T64: =+IF(R64<>"",ABS(R64),0) -> #REF! | V64: =+IF(S64<>"",ABS(S64),0) -> #REF!
H65: =+H23 -> 20 | I65: =+I23 -> Rechazo Final Los Colorados | J65: =+#REF! -> #REF! | K65: =+#REF! -> #REF! | L65: Pérd | M65: 108284.66 | N65: 0.12974458 | O65: =+M65*N65 -> 14049.347 | R65: =+IF(J65<>0,(M65-J65)/J65,0) -> #REF! | S65: =+IF(K65<>0,(N65-K65)/K65,0) -> #REF! | T65: =+IF(R65<>"",ABS(R65),0) -> #REF! | V65: =+IF(S65<>"",ABS(S65),0) -> #REF!
H66: =+H24 -> 21 | I66: =+I24 -> Producción Planta Rechazo a Stock P40 | J66: =+#REF! -> #REF! | K66: =+#REF! -> #REF! | M66: 18819.257 | N66: 0.39867 | O66: =+M66*N66 -> 7502.6732 | R66: =+IF(J66<>0,(M66-J66)/J66,0) -> #REF! | S66: =+IF(K66<>0,(N66-K66)/K66,0) -> #REF! | T66: =+IF(R66<>"",ABS(R66),0) -> #REF! | V66: =+IF(S66<>"",ABS(S66),0) -> #REF! | W66: 0.03
D67: =+#REF! -> #REF! | E67: =+#REF! -> #REF! | F67: =+#REF! -> #REF! | G67: =+IF(D67>0,1,IF(D67<>0,-1,0)) -> #REF! | H67: =+H25 -> 22 | I67: =+I25 -> Delta Stock P40 | J67: =+E67 -> #REF! | K67: =+F67 -> #REF! | L67: Inv | M67: 311.60807 | N67: 0.3775584 | O67: =+M67*N67 -> 117.65024 | P67: =+#REF! -> #REF! | Q67: =+M67-J67 -> #REF! | R67: =+IF(J67<>0,(M67-J67)/J67,0) -> #REF! | S67: =+IF(K67<>0,(N67-K67)/K67,0) -> #REF! | T67: =+IF(R67<>"",ABS(R67),0) -> #REF! | V67: =+IF(S67<>"",ABS(S67),0) -> #REF!
H68: =+H26 -> 23 | I68: =+I26 -> Venta desde P40 | J68: =+#REF! -> #REF! | K68: =+#REF! -> #REF! | L68: Venta | M68: 19130.865 | N68: 0.39832613 | O68: =+M68*N68 -> 7620.3234 | R68: =+IF(J68<>0,(M68-J68)/J68,0) -> #REF! | S68: =+IF(K68<>0,(N68-K68)/K68,0) -> #REF! | T68: =+IF(R68<>"",ABS(R68),0) -> #REF! | U68: 0 | V68: =+IF(S68<>"",ABS(S68),0) -> #REF! | W68: 0.01
H69: =+H27 -> 24 | I69: =+I27 -> de Stoc Prec a Nodo Alim Planta de Pellet | J69: =+#REF! -> #REF! | K69: =+#REF! -> #REF! | L69: Produc | M69: 673884.94 | N69: 0.60967226 | O69: =+M69*N69 -> 410848.96 | R69: =+IF(J69<>0,(M69-J69)/J69,0) -> #REF! | S69: =+IF(K69<>0,(N69-K69)/K69,0) -> #REF! | T69: =+IF(R69<>"",ABS(R69),0) -> #REF! | U69: 0 | V69: =+IF(S69<>"",ABS(S69),0) -> #REF! | W69: 0
I70: 73294
J71: % Incertidumbre | M71: Desv estándar | R71: =+#REF! -> #REF!
J72: TMSD | K72: %Fe T | M72: TMSD | N72: %Fe T
I73: =+I46 -> Alimentación Mina | J73: 99 | K73: 10 | M73: =+J73*J46/100 -> #REF! | N73: =+K73*K46/100 -> #REF!
I74: =+I47 -> Alim a Planta desde Acopio Mina | J74: 99 | K74: 99 | M74: =+J74*J47/100 -> #REF! | N74: =+K74*K47/100 -> #REF!
I75: =+I48 -> Acopio Mina a Terceros | J75: 0.1 | K75: 1 | M75: =+J75*J48/100 -> #REF! | N75: =+K75*K48/100 -> #REF!
I76: =+I49 -> Delta S Acopio Mina | J76: 99 | K76: 30 | M76: =+J76*J49/100 -> #REF! | N76: =+K76*K49/100 -> #REF!
I77: =+I50 -> Alim a Chancado | J77: 99 | K77: 30 | M77: =+J77*J50/100 -> #REF! | N77: =+K77*K50/100 -> #REF!
I78: =+I51 -> Chanc a Stock Prec Los Col. | J78: 99 | K78: 30 | M78: =+J78*J51/100 -> 0 | N78: =+K78*K51/100 -> 0
I79: =+I52 -> Chanc a Stock Grueso | J79: 99 | K79: 30 | M79: =+J79*J52/100 -> #REF! | N79: =+K79*K52/100 -> #REF!
I80: =+I53 -> Delta Stock de Grueso | J80: 99 | K80: 30 | M80: =+J80*J53/100 -> #REF! | N80: =+K80*K53/100 -> #REF!
I81: =+I54 -> De Stock Grueso a conc magn (alim A52 y A82) | J81: 99 | K81: 30 | M81: =+J81*J54/100 -> #REF! | N81: =+K81*K54/100 -> #REF!
I82: =+I55 -> Stock Prec a (o desde) Acopio Mina | J82: 99 | K82: 30 | M82: =+J82*J55/100 -> #REF! | N82: =+K82*K55/100 -> #REF!
I83: =+I56 -> Delta Stock Prec | J83: 99 | K83: 30 | M83: =+J83*J56/100 -> #REF! | N83: =+K83*K56/100 -> #REF!
I84: =+I57 -> de Stock Prec a Terceros (a otras faenas) | J84: 0.1 | K84: 1 | M84: =+J84*J57/100 -> #REF! | N84: =+K84*K57/100 -> #REF!
... I96: =+I69 -> de Stoc Prec a Nodo Alim Planta de Pellet | J96: 99 | K96: 30 | M96: =+J96*J69/100 -> #REF! | N96: =+K96*K69/100 -> #REF!
J98: Dif Cudráticas
J99: TMSD | K99: %Fe T
I100: =+I73 -> Alimentación Mina | J100: =+IF(M73<>0,(M46-J46)^2/M73,"") -> #REF! | K100: =+IF(N73<>0,(N46-K46)^2/N73,"") -> #REF!
I101: =+I74 -> Alim a Planta desde Acopio Mina | J101: =+IF(M74<>0,(M47-J47)^2/M74,"") -> #REF! | K101: =+IF(N74<>0,(N47-K47)^2/N74,"") -> #REF!
I102: =+I75 -> Acopio Mina a Terceros | J102: =+IF(M75<>0,(M48-J48)^2/M75,"") -> #REF! | K102: =+IF(N75<>0,(N48-K48)^2/N75,"") -> #REF!
I103: =+I76 -> Delta S Acopio Mina | J103: =+IF(M76<>0,(M49-J49)^2/M76,"") -> #REF! | K103: =+IF(N76<>0,(N49-K49)^2/N76,"") -> #REF!
I104: =+I77 -> Alim a Chancado | J104: =+IF(M77<>0,(M50-J50)^2/M77,"") -> #REF! | K104: =+IF(N77<>0,(N50-K50)^2/N77,"") -> #REF!
I105: =+I78 -> Chanc a Stock Prec Los Col. | J105: =+IF(M78<>0,(M51-J51)^2/M78,"") | K105: =+IF(N78<>0,(N51-K51)^2/N78,"")
I106: =+I79 -> Chanc a Stock Grueso | J106: =+IF(M79<>0,(M52-J52)^2/M79,"") -> #REF! | K106: =+IF(N79<>0,(N52-K52)^2/N79,"") -> #REF!
I107: =+I80 -> Delta Stock de Grueso | J107: =+IF(M80<>0,(M53-J53)^2/M80,"") -> #REF! | K107: =+IF(N80<>0,(N53-K53)^2/N80,"") -> #REF!
I108: =+I81 -> De Stock Grueso a conc magn (alim A52 y A82) | J108: =+IF(M81<>0,(M54-J54)^2/M81,"") -> #REF! | K108: =+IF(N81<>0,(N54-K54)^2/N81,"") -> #REF!
I109: =+I82 -> Stock Prec a (o desde) Acopio Mina | J109: =+IF(M82<>0,(M55-J55)^2/M82,"") -> #REF! | K109: =+IF(N82<>0,(N55-K55)^2/N82,"") -> #REF!
I110: =+I83 -> Delta Stock Prec | J110: =+IF(M83<>0,(M56-J56)^2/M83,"") -> #REF! | K110: =+IF(N83<>0,(N56-K56)^2/N83,"") -> #REF!
I111: =+I84 -> de Stock Prec a Terceros (a otras faenas) | J111: =+IF(M84<>0,(M57-J57)^2/M84,"") -> #REF! | K111: =+IF(N84<>0,(N57-K57)^2/N84,"") -> #REF!
... I123: =+I96 -> de Stoc Prec a Nodo Alim Planta de Pellet | J123: =+IF(M96<>0,(M69-J69)^2/M96,"") -> #REF! | K123: =+IF(N96<>0,(N69-K69)^2/N96,"") -> #REF!

Sheet Diag Proc Los Colorados
F6: =+'Bal Los Colorados'!M47 -> 0 | I6: =+'Bal Los Colorados'!M46 -> 502781.82
E7: =+-C8+D16-F6 -> 1770.5762 | F7: =+'Bal Los Colorados'!N47 -> 0 | I7: =+'Bal Los Colorados'!N46 -> 0.46140051 | P7: Planta Beneficio
C8: =+'Bal Los Colorados'!M48 -> 12961.629 | F8: =+'Bal Los Colorados'!O47 -> 0 | I8: =+'Bal Los Colorados'!O46 -> 231983.79 | P8: Rp | Q8: =+I25/K20 -> 0.75353481
C9: =+'Bal Los Colorados'!N48 -> 0.59443308 | P9: Rm | Q9: =+I27/K22 -> 0.91700161
C10: =+'Bal Los Colorados'!O48 -> 7704.8211 | P10: Planta Rechazos
J11: =+'Bal Los Colorados'!M52 -> 502781.82 | P11: Rp | Q11: =+O33/(P22+M30) -> 0.14806198
H12: =+'Bal Los Colorados'!M50 -> 502781.82 | J12: =+'Bal Los Colorados'!N52 -> 0.46140051 | P12: Rm | Q12: =+O35/(P24+M32) -> 0.34811925
H13: =+'Bal Los Colorados'!N50 -> 0.46140051 | J13: =+'Bal Los Colorados'!O52 -> 231983.79 | P13: Planta Global
H14: =+'Bal Los Colorados'!O50 -> 231983.79 | P14: Rp | Q14: =+(O33+I25)/(K20+(M30+P22-(L25-M15))) -> 0.72448459
M15: =+'Bal Los Colorados'!M60 -> 30174.414 | P15: Rm | Q15: =+(O34+I27)/(K22+(M32+P24-(L27-M17))) -> 0.87798736
D16: =+'Bal Los Colorados'!M55 -> 14732.205 | M16: =+'Bal Los Colorados'!N60 -> 0.19850416
D17: =+'Bal Los Colorados'!N55 -> 0.60105751 | M17: =+'Bal Los Colorados'!O60 -> 5989.7466
D18: =+'Bal Los Colorados'!O55 -> 8854.9026
J19: =+J11-K20 -> 44584.89 | X19: 13390 | Y19: =+J11+X20 -> 542951.82
K20: =+'Bal Los Colorados'!M54 -> 458196.93 | O20: =+M15-P22 -> -14174.322 | X20: =+X19*3 -> 40170
K21: =+'Bal Los Colorados'!N54 -> 0.47167819
K22: =+'Bal Los Colorados'!O54 -> 216121.5 | P22: =+'Bal Los Colorados'!M63 -> 44348.737
P23: =+'Bal Los Colorados'!N63 -> 0.21655702
P24: =+'Bal Los Colorados'!O63 -> 9604.0304
I25: =+'Bal Los Colorados'!M58 -> 345267.34 | L25: =+'Bal Los Colorados'!M59 -> 112929.59
I26: =+'Bal Los Colorados'!N58 -> 0.5740009 | L26: =+'Bal Los Colorados'!N59 -> 0.15884
G27: =+I25-C28-G36-D16 -> -359512.14 | I27: =+'Bal Los Colorados'!O58 -> 198183.76 | L27: =+'Bal Los Colorados'!O59 -> 17937.737
C28: =+'Bal Los Colorados'!M57 -> 16162.331 | S28: =+'Bal Los Colorados'!M65 -> 108284.66
C29: =+'Bal Los Colorados'!N57 -> 0.59864253 | S29: =+'Bal Los Colorados'!N65 -> 0.12974458
C30: =+'Bal Los Colorados'!O57 -> 9675.4587 | M30: =+'Bal Los Colorados'!M61 -> 82755.179 | S30: =+'Bal Los Colorados'!O65 -> 14049.347
M31: =+'Bal Los Colorados'!N61 -> 0.14437755
I32: =+I25-D16 -> 330535.13 | M32: =+'Bal Los Colorados'!O61 -> 11947.99
O33: =+'Bal Los Colorados'!M66 -> 18819.257
O34: =+'Bal Los Colorados'!N66 -> 0.39867
O35: =+'Bal Los Colorados'!O66 -> 7502.6732
G36: =+'Bal Los Colorados'!M69 -> 673884.94 | S36: =+'Bal Los Colorados'!M68 -> 19130.865
G37: =+'Bal Los Colorados'!N69 -> 0.60967226 | S37: =+'Bal Los Colorados'!N68 -> 0.39832613
G38: =+'Bal Los Colorados'!O69 -> 410848.96 | S38: =+'Bal Los Colorados'!O68 -> 7620.3234
P40: =+O33-S36 -> -311.60807
E43: BALANCE GLOBAL MASA
E44: ENTRADAS | H44: VARIACIONES DE INVENTARIOS | K44: SALIDAS
E45: ALIMENTACIÓN MINA | G45: =+I6 -> 502781.82 | H45: ACOPIO MINA | J45: =+E7 -> 1770.5762 | K45: VENTAS DESDE ACOPIO MINA | N45: =+C8 -> 12961.629
H46: STOCK GRUESO | J46: =+J19 -> 44584.89 | K46: VENTAS DE STOCK PRECONC | N46: =+C28 -> 16162.331
H47: STOCK PRE CONCENTRADO | J47: =+G27 -> -359512.14 | K47: VENTA DESDE STOC P4O | N47: =+S36 -> 19130.865
H48: STOCK RECHAZO | J48: =+O20 -> -14174.322 | K48: RECHAZO FINAL | N48: =+S28 -> 108284.66
H49: STOCK P-40 | J49: =+P40 -> -311.60807 | K49: A PLANTA DE PELLETS | N49: =+G36 -> 673884.94
E50: TOTAL ENTRADAS | G50: =+G45 -> 502781.82 | H50: VAR NETA | J50: =+SUM(J45:J49) -> -327642.61 | K50: TOTAL SALIDAS | N50: =+SUM(N45:N49) -> 830424.43
J52: ENTRADAS - VAR INVENTARIO - SALIDAS | N52: =+G50-J50-N50 -> 1.5599653e-08
E54: BALANCE GLOBAL FINO
E55: ENTRADAS | H55: VARIACIONES DE INVENTARIOS | K55: SALIDAS
E56: ALIMENTACIÓN MINA | G56: =+I8 -> 231983.79 | H56: ACOPIO MINA | J56: =+'Bal Los Colorados'!O49*'Bal Los Colorados'!G49 -> #REF! | K56: VENTAS DESDE ACOPIO MINA | N56: =+C10 -> 7704.8211
H57: STOCK GRUESO | J57: =+'Bal Los Colorados'!O53*'Bal Los Colorados'!G53 -> #REF! | K57: VENTAS DE STOCK PRECONC | N57: =+C30 -> 9675.4587
H58: STOCK PRE CONCENTRADO | J58: =+'Bal Los Colorados'!O56*'Bal Los Colorados'!G56 -> #REF! | K58: VENTA DESDE STOC P4O | N58: =+S38 -> 7620.3234
H59: STOCK RECHAZO | J59: =+'Bal Los Colorados'!O62*'Bal Los Colorados'!G62 -> #REF! | K59: RECHAZO FINAL | N59: =+S30 -> 14049.347
H60: STOCK P-40 | J60: =+'Bal Los Colorados'!O67*'Bal Los Colorados'!G67 -> #REF! | K60: A PLANTA DE PELLETS | N60: =+G38 -> 410848.96
E61: TOTAL ENTRADAS | G61: =+G56 -> 231983.79 | H61: VAR NETA | J61: =+SUM(J56:J60) -> #REF! | K61: TOTAL SALIDAS | N61: =+SUM(N56:N60) -> 449898.91
J63: ENTRADAS - VAR INVENTARIO - SALIDAS | N63: =+G61-J61-N61 -> #REF!

Sheet Datos Extra
A1: Pellets Basico | B1: 66753 | C1: 0 | D1: 0 | E1: 0
A2: Pellets Chips | B2: 24736 | C2: 0 | D2: 0 | E2: 0
A3: Pellets Feed | B3: 50490 | C3: 0 | D3: 0 | E3: 0
A4: Alimentacion Silos | B4: 0 | C4: 0 | D4: 0 | E4: 0
A5: Concentrado | B5: 0 | C5: 0 | D5: 0 | E5: 0
A6: Colas | B6: 0 | C6: 0 | D6: 0 | E6: 0
A7: Preconcentrado | B7: 150617 | C7: 0 | D7: 0 | E7: 0
A8: Sinter | B8: 435811 | C8: 0 | D8: 0 | E8: 0
A9: Finos Huasco | B9: 2203 | C9: 0 | D9: 0 | E9: 0
A10: Granzas Cristales PP | B10: 27 | C10: 0 | D10: 0 | E10: 0
A11: Granzas Cristales | B11: 25122 | C11: 0 | D11: 0 | E11: 0
A12: Costo Mina | B12: 841140 | C12: 1 | D12: 2.65 | E12: 0
... A37: Producto Pila Chank a stock Sinter | B37: 0 | C37: 0 | D37: 0 | E37: 0
A38: Preconcentrado | B38: 149936 | C38: 150934.6 | D38: 998.60122 | E38: 0.0096968122 | F38: 1453.9012 | G38: 149616.66 | H38: 148482.1
A39: Sinter | B39: 435765 | C39: 395463 | D39: -40302 | E39: 0.0096713366 | F39: 149046.44 | G39: 434139.57 | H39: 431550.57
A40: Silos | B40: 0 | C40: -2927.9472 | D40: -2927.9472 | E40: 0.0086 | F40: 8030.34 | G40: 0 | H40: 0
A41: TK Filtrado | B41: 0 | C41: -1980 | D41: -1980 | E41: 0 | F41: 2700 | G41: 0 | H41: 0
A42: Pellet Feed | B42: 48104 | C42: 147374 | D42: 99270 | E42: 0.076449042 | F42: -350455.26 | G42: 46202.703 | H42: 44426.495
A43: Pila de emergencia | B43: 0 | C43: 0 | D43: 0 | E43: 0 | F43: 0 | G43: 0 | H43: 0
A44: Pellet Producto | B44: 65746 | C44: 14273.092 | D44: -51472.908 | E44: 0.005 | F44: -275163.14 | G44: 67260.881 | H44: 65417.27
A45: Chips | B45: 24742 | C45: 12095.744 | D45: -12646.256 | E45: 0.005 | F45: -364.17 | G45: 24982.46 | H45: 24618.29
A46: Finos | B46: 2203 | C46: 1837.275 | D46: -365.72502 | E46: 0.035 | F46: 2125.4149 | G46: 0.48008606 | H46: 2125.895
A47: Derrames Molienda | B47: 0 | C47: 0 | D47: 0 | E47: 0 | F47: 0 | G47: 0 | H47: 0
A48: MN1 | B48: 0 | C48: 115642 | D48: 112764 | F48: 68.85 | G48: 7.7
A49: MN2 | B49: 0 | C49: 0 | D49: 0 | F49: 68.77 | G49: 7.74
A50: MN3 | B50: 0 | C50: 0 | D50: 0 | F50: 69.15 | G50: 7.37
A51: MN4 | B51: 0 | C51: 0 | D51: 0 | F51: 69.15 | G51: 7.37
A52: MN1 | B52: 0 | C52: 0 | D52: 0 | F52: 65.34 | G52: 1.12
A53: MN2 | B53: 0 | C53: 0 | D53: 0 | F53: 65.18 | G53: 0.69
A54: MN3 | B54: 0 | C54: 0 | D54: 0 | F54: 65.55 | G54: 0.71
A55: MN4 | B55: 0 | C55: 0 | D55: 0
A56: MN1 | B56: 0 | C56: 62770 | D56: 65510 | F56: 64.07 | G56: 1.19
A57: MN2 | B57: 0 | C57: 136102 | D57: 139489 | F57: 64.07 | G57: 1.19
A58: MN3 | B58: 0 | C58: 0 | D58: 0
A59: MN4 | B59: 0 | C59: 0 | D59: 0
A60: MN1 | B60: 0 | C60: 67282 | D60: 66000
A61: MN2 | B61: 0 | C61: 0 | D61: 0

Sheet Utilidad
A1: 388479 | B1: 388479 | C1: 61.25 | D1: 61.63158 | E1: 0.0092167453 | F1: =D1*B1 -> 23942575 | H1: Recepcion (Ferronor + Camiones) | K1: =C1/100 -> 0.6125
A2: 163082 | B2: 163082 | C2: 63.3 | D2: 63.39236 | E2: 0.0095301 | F2: =D2*B2 -> 10338153 | H2: A Sinter Feed
A3: 202642 | B3: 202642 | C3: 63.7 | D3: 63.386388 | E3: 0.0115 | F3: =D3*B3 -> 12844744 | H3: Embarque Sinter Feed
A4: 225397 | B4: 225397 | C4: 59.76 | D4: 60.3576 | E4: 0.0089899 | F4: =D4*B4 -> 13604422 | H4: A Preconcentrado
A5: 228628 | B5: 228628 | C5: 60.29 | D5: 59.6871 | E5: 0.0089899 | F5: =D5*B5 -> 13646142 | H5: Alim Silos Molienda
A6: -2903 | B6: -4354.5 | C6: 60.29 | D6: 63.3045 | E6: 0.0086 | F6: =D6*B6 -> -275659.45 | H6: Delta Stock Silos Molienda
A7: 231530 | B7: 229834.02 | C7: 58.82 | D7: 60.589335 | E7: 0.0076 | F7: =D7*B7 -> 13925491 | H7: Aliment Molienda Clasificación
A8: -2106 | B8: -2106 | C8: 68.65 | D8: 68.65 | E8: 0 | F8: =D8*B8 -> -144576.9 | H8: EMISARIO SUBMARINO
A9: 1021 | B9: 969.95 | C9: 11.31 | D9: 11.1969 | E9: 0 | F9: =D9*B9 -> 10860.433 | H9: Alimentación a TK Inventarios
A10: 23778 | B10: 21060.024 | C10: 11.31 | D10: 10.7445 | E10: 0 | F10: =D10*B10 -> 226279.42 | H10: Alimentación Filtrado
A11: 22756 | B11: 20480.4 | C11: 11.31 | D11: 10.5183 | E11: 0 | F11: =D11*B11 -> 215418.99 | H11: Derrames
A12: 208774 | B12: 208774 | C12: 68.7 | D12: 66.639 | E12: 0.009954634 | F12: =D12*B12 -> 13912491 | H12: Filtro a nodo
A13: 210880 | B13: 210880 | C13: 68.65 | D13: 67.9635 | E13: 0.083495571 | F13: =D13*B13 -> 14332143 | H13: Pellet feed a Stock Final
... A27: -51216 | B27: -35851.2 | C27: 0 | D27: 0 | E27: 0.005 | F27: =D27*B27 -> 0 | H27: Delta Stock Pila intermedia
A28: 0 | B28: 0 | C28: 0 | D28: 0 | E28: 0
A29: 0 | B29: 0 | C29: 0 | D29: 0 | E29: 0.01
A30: 0 | B30: 0 | C30: 68.65 | D30: 68.65 | E30: 0.01
A31: 989 | B31: 692.3 | C31: 59.76 | D31: 56.772 | E31: 0.0096968122
A32: 91681 | B32: 88265 | C32: 68.65 | D32: 68.614693 | E32: 0.076449042
A33: -39912 | B33: -39560 | C33: 63.3 | D33: 63.361769 | E33: 0.0096713366
A34: -12583 | B34: -16357.9 | C34: 65 | D34: 68.25 | E34: 0.005
A35: 65670 | B35: 65670 | C35: 65 | D35: 65 | E35: 0.005
A36: 0 | B36: 0 | C36: 82.99 | D36: 90.836856 | E36: 0.82988351
A37: 0 | B37: 0 | C37: 96.87 | D37: 99.906645 | E37: 0.96866078
N65: Valores Calculados
N66: TMS | O66: %FeT | P66: TMF Fe | Q66: Humedad
N67: =B1 -> 388479 | O67: =IF(D$1>1,D1/100,D1) -> 0.6163158 | P67: =N67*O67 -> 239425.75 | Q67: =E1 -> 0.0092167453
N68: =B2 -> 163082 | O68: =IF(D$1>1,D2/100,D2) -> 0.6339236 | P68: =N68*O68 -> 103381.53 | Q68: =E2 -> 0.0095301
N69: 642376.55 | O69: =IF(D$1>1,D3/100,D3) -> 0.63386388 | P69: =N69*O69 -> 407179.29 | Q69: =E3 -> 0.0115
N70: =B4 -> 225397 | O70: =IF(D$1>1,D4/100,D4) -> 0.603576 | P70: =N70*O70 -> 136044.22 | Q70: =E4 -> 0.0089899
N71: =B5 -> 228628 | O71: =IF(D$1>1,D5/100,D5) -> 0.596871 | P71: =N71*O71 -> 136461.42 | Q71: =E5 -> 0.0089899
N72: =B6 -> -4354.5 | O72: =IF(D$1>1,D6/100,D6) -> 0.633045 | P72: =N72*O72 -> -2756.5945 | Q72: =E6 -> 0.0086
N73: =B7 -> 229834.02 | O73: =IF(D$1>1,D7/100,D7) -> 0.60589335 | P73: =N73*O73 -> 139254.91 | Q73: =E7 -> 0.0076
N74: =B8 -> -2106 | O74: =IF(D$1>1,D8/100,D8) -> 0.6865 | P74: =N74*O74 -> -1445.769 | Q74: =E8 -> 0
N75: =B9 -> 969.95 | O75: =IF(D$1>1,D9/100,D9) -> 0.111969 | P75: =N75*O75 -> 108.60433 | Q75: =E9 -> 0
N76: =B10 -> 21060.024 | O76: =IF(D$1>1,D10/100,D10) -> 0.107445 | P76: =N76*O76 -> 2262.7942 | Q76: =E10 -> 0
N77: =B11 -> 20480.4 | O77: =IF(D$1>1,D11/100,D11) -> 0.105183 | P77: =N77*O77 -> 2154.1899 | Q77: =E11 -> 0
N78: =B12 -> 208774 | O78: =IF(D$1>1,D12/100,D12) -> 0.66639 | P78: =N78*O78 -> 139124.91 | Q78: =E12 -> 0.009954634
N79: =B13 -> 210880 | O79: =IF(D$1>1,D13/100,D13) -> 0.679635 | P79: =N79*O79 -> 143321.43 | Q79: =E13 -> 0.083495571
N80: =B14 -> 0 | O80: =IF(D$1>1,D14/100,D14) -> 0.58 | P80: =N80*O80 -> 0 | Q80: =E14 -> 0
N81: =B15 -> 192143 | O81: =IF(D$1>1,D15/100,D15) -> 0.6865 | P81: =N81*O81 -> 131906.17 | Q81: =E15 -> 0.083495571
... N126: =B60 -> 0 | O126: =IF(D$1>1,D60/100,D60) -> 0 | P126: =N126*O126 -> 0 | Q126: =E60 -> 0

Sheet Flujos
B2: Mediciones | F2: Balance | J2: % Cambio relativo | M2: Max Var Ton | N2: Max Var FeT
B3: Flujos | C3: TMS | D3: %FeT | F3: Flujos | G3: TMS | H3: %FeT | J3: TMSD | K3: %Fe T | Q3: Flujos | R3: Humedad
A4: 0 | B4: Recepcion (Ferronor + Camiones) | C4: =Utilidad!A1 -> 388479 | D4: =IF(Utilidad!C1>1,Utilidad!C1/100,Utilidad!C1) -> 0.6125 | F4: Recepcion (Ferronor + Camiones) | G4: =Utilidad!B1 -> 388479 | H4: =IF(Utilidad!D1>1,Utilidad!D1/100,Utilidad!D1) -> 0.6163158 | J4: =+IF(C4<>0,(G4-C4)/C4,ABS(G4-C4)) -> 0 | K4: =+IF(D4<>0,(H4-D4)/D4,0) -> 0.0062298849 | M4: =+IF(J4<>"",ABS(J4),0) -> 0 | N4: =+IF(J4<>"",ABS(K4),0) -> 0.0062298849 | Q4: Recepcion (Ferronor + Camiones) | R4: =Utilidad!E1 -> 0.0092167453
A5: 1 | B5: A Sinter Feed | C5: =Utilidad!A2 -> 163082 | D5: =IF(Utilidad!C2>1,Utilidad!C2/100,Utilidad!C2) -> 0.633 | F5: A Sinter Feed | G5: =Utilidad!B2 -> 163082 | H5: =IF(Utilidad!D2>1,Utilidad!D2/100,Utilidad!D2) -> 0.6339236 | J5: =+IF(C5<>0,(G5-C5)/C5,ABS(G5-C5)) -> 0 | K5: =+IF(D5<>0,(H5-D5)/D5,0) -> 0.001459076 | M5: =+IF(J5<>"",ABS(J5),0) -> 0 | N5: =+IF(J5<>"",ABS(K5),0) -> 0.001459076 | Q5: A Sinter Feed | R5: =Utilidad!E2 -> 0.0095301
A6: 2 | B6: Embarque Sinter Feed | C6: =Utilidad!A3 -> 202642 | D6: =IF(Utilidad!C3>1,Utilidad!C3/100,Utilidad!C3) -> 0.637 | F6: Embarque Sinter Feed | G6: =Utilidad!B3 -> 202642 | H6: =IF(Utilidad!D3>1,Utilidad!D3/100,Utilidad!D3) -> 0.63386388 | J6: =+IF(C6<>0,(G6-C6)/C6,ABS(G6-C6)) -> 0 | K6: =+IF(D6<>0,(H6-D6)/D6,0) -> -0.004923273 | M6: =+IF(J6<>"",ABS(J6),0) -> 0 | N6: =+IF(J6<>"",ABS(K6),0) -> 0.004923273 | Q6: Embarque Sinter Feed | R6: =Utilidad!E3 -> 0.0115
A7: 3 | B7: A Preconcentrado | C7: =Utilidad!A4 -> 225397 | D7: =IF(Utilidad!C4>1,Utilidad!C4/100,Utilidad!C4) -> 0.5976 | F7: A Preconcentrado | G7: =Utilidad!B4 -> 225397 | H7: =IF(Utilidad!D4>1,Utilidad!D4/100,Utilidad!D4) -> 0.603576 | J7: =+IF(C7<>0,(G7-C7)/C7,ABS(G7-C7)) -> 0 | K7: =+IF(D7<>0,(H7-D7)/D7,0) -> 0.01 | M7: =+IF(J7<>"",ABS(J7),0) -> 0 | N7: =+IF(J7<>"",ABS(K7),0) -> 0.01 | Q7: A Preconcentrado | R7: =Utilidad!E4 -> 0.0089899
A8: 4 | B8: Alim Silos Molienda | C8: =Utilidad!A5 -> 228628 | D8: =IF(Utilidad!C5>1,Utilidad!C5/100,Utilidad!C5) -> 0.6029 | F8: Alim Silos Molienda | G8: =Utilidad!B5 -> 228628 | H8: =IF(Utilidad!D5>1,Utilidad!D5/100,Utilidad!D5) -> 0.596871 | J8: =+IF(C8<>0,(G8-C8)/C8,ABS(G8-C8)) -> 0 | K8: =+IF(D8<>0,(H8-D8)/D8,0) -> -0.01 | M8: =+IF(J8<>"",ABS(J8),0) -> 0 | N8: =+IF(J8<>"",ABS(K8),0) -> 0.01 | Q8: Alim Silos Molienda | R8: =Utilidad!E5 -> 0.0089899
A9: 5 | B9: Delta Stock Silos Molienda | C9: =Utilidad!A6 -> -2903 | D9: =IF(Utilidad!C6>1,Utilidad!C6/100,Utilidad!C6) -> 0.6029 | F9: Delta Stock Silos Molienda | G9: =Utilidad!B6 -> -4354.5 | H9: =IF(Utilidad!D6>1,Utilidad!D6/100,Utilidad!D6) -> 0.633045 | J9: =+IF(C9<>0,(G9-C9)/C9,ABS(G9-C9)) -> 0.5 | K9: =+IF(D9<>0,(H9-D9)/D9,0) -> 0.05 | M9: =+IF(J9<>"",ABS(J9),0) -> 0.5 | N9: =+IF(J9<>"",ABS(K9),0) -> 0.05 | Q9: Delta Stock Silos Molienda | R9: =Utilidad!E6 -> 0.0086
A10: 6 | B10: Aliment Molienda Clasificación | C10: =Utilidad!A7 -> 231530 | D10: =IF(Utilidad!C7>1,Utilidad!C7/100,Utilidad!C7) -> 0.5882 | F10: Aliment Molienda Clasificación | G10: =Utilidad!B7 -> 229834.02 | H10: =IF(Utilidad!D7>1,Utilidad!D7/100,Utilidad!D7) -> 0.60589335 | J10: =+IF(C10<>0,(G10-C10)/C10,ABS(G10-C10)) -> -0.0073250824 | K10: =+IF(D10<>0,(H10-D10)/D10,0) -> 0.030080503 | M10: =+IF(J10<>"",ABS(J10),0) -> 0.0073250824 | N10: =+IF(J10<>"",ABS(K10),0) -> 0.030080503 | Q10: Aliment Molienda Clasificación | R10: =Utilidad!E7 -> 0.0076
A11: 7 | B11: Delta stock colas | C11: =Utilidad!A8 -> -2106 | D11: =IF(Utilidad!C8>1,Utilidad!C8/100,Utilidad!C8) -> 0.6865 | F11: Delta stock colas | G11: =Utilidad!B8 -> -2106 | H11: =IF(Utilidad!D8>1,Utilidad!D8/100,Utilidad!D8) -> 0.6865 | J11: =+IF(C11<>0,(G11-C11)/C11,ABS(G11-C11)) -> 0 | K11: =+IF(D11<>0,(H11-D11)/D11,0) -> 0 | M11: =+IF(J11<>"",ABS(J11),0) -> 0 | N11: =+IF(J11<>"",ABS(K11),0) -> 0 | Q11: Delta stock colas | R11: =Utilidad!E8 -> 0
A12: 8 | B12: Delta stock relave | C12: =Utilidad!A9 -> 1021 | D12: =IF(Utilidad!C9>1,Utilidad!C9/100,Utilidad!C9) -> 0.1131 | F12: Delta stock relave | G12: =Utilidad!B9 -> 969.95 | H12: =IF(Utilidad!D9>1,Utilidad!D9/100,Utilidad!D9) -> 0.111969 | J12: =+IF(C12<>0,(G12-C12)/C12,ABS(G12-C12)) -> -0.05 | K12: =+IF(D12<>0,(H12-D12)/D12,0) -> -0.01 | M12: =+IF(J12<>"",ABS(J12),0) -> 0.05 | N12: =+IF(J12<>"",ABS(K12),0) -> 0.01 | Q12: Delta stock relave | R12: =Utilidad!E9 -> 0
A13: 9 | B13: Molienda a relave | C13: =Utilidad!A10 -> 23778 | D13: =IF(Utilidad!C10>1,Utilidad!C10/100,Utilidad!C10) -> 0.1131 | F13: Molienda a relave | G13: =Utilidad!B10 -> 21060.024 | H13: =IF(Utilidad!D10>1,Utilidad!D10/100,Utilidad!D10) -> 0.107445 | J13: =+IF(C13<>0,(G13-C13)/C13,ABS(G13-C13)) -> -0.11430635 | K13: =+IF(D13<>0,(H13-D13)/D13,0) -> -0.05 | M13: =+IF(J13<>"",ABS(J13),0) -> 0.11430635 | N13: =+IF(J13<>"",ABS(K13),0) -> 0.05 | Q13: Molienda a relave | R13: =Utilidad!E10 -> 0
A14: 10 | B14: DRF | C14: =Utilidad!A11 -> 22756 | D14: =IF(Utilidad!C11>1,Utilidad!C11/100,Utilidad!C11) -> 0.1131 | F14: DRF | G14: =Utilidad!B11 -> 20480.4 | H14: =IF(Utilidad!D11>1,Utilidad!D11/100,Utilidad!D11) -> 0.105183 | J14: =+IF(C14<>0,(G14-C14)/C14,ABS(G14-C14)) -> -0.1 | K14: =+IF(D14<>0,(H14-D14)/D14,0) -> -0.07 | M14: =+IF(J14<>"",ABS(J14),0) -> 0.1 | N14: =+IF(J14<>"",ABS(K14),0) -> 0.07 | Q14: EMISARIO SUBMARINO | R14: =Utilidad!E11 -> 0
A15: 11 | B15: Alimentación a TK Inventarios | C15: =Utilidad!A12 -> 208774 | D15: =IF(Utilidad!C12>1,Utilidad!C12/100,Utilidad!C12) -> 0.687 | F15: Alimentación a TK Inventarios | G15: =Utilidad!B12 -> 208774 | H15: =IF(Utilidad!D12>1,Utilidad!D12/100,Utilidad!D12) -> 0.66639 | J15: =+IF(C15<>0,(G15-C15)/C15,ABS(G15-C15)) -> 0 | K15: =+IF(D15<>0,(H15-D15)/D15,0) -> -0.03 | M15: =+IF(J15<>"",ABS(J15),0) -> 0 | N15: =+IF(J15<>"",ABS(K15),0) -> 0.03 | Q15: Alimentación a TK Inventarios | R15: =Utilidad!E12 -> 0.009954634
... A40: 36 | B40: Rm | C40: =Utilidad!A37 -> 0 | D40: =IF(Utilidad!C37>1,Utilidad!C37/100,Utilidad!C37) -> 0.9687 | F40: Rm | G40: =Utilidad!B37 -> 0 | H40: =IF(Utilidad!D37>1,Utilidad!D37/100,Utilidad!D37) -> 0.99906645 | J40: =+IF(C40<>0,(G40-C40)/C40,ABS(G40-C40)) -> 0 | K40: =+IF(D40<>0,(H40-D40)/D40,0) -> 0.031347633 | M40: =+IF(J40<>"",ABS(J40),0) -> 0 | N40: =+IF(J40<>"",ABS(K40),0) -> 0.031347633 | Q40: Rm | R40: =Utilidad!E37 -> 0.96866078

Sheet Diagrama
U3: Planta de Harneo | W3: Total Ali. | X3: =+S15+V13+X13 -> 33411.24 | AU3: =+AU8*AU10/100 -> 0 | AV3: =+AV8*AV10/100 -> 0 | AW3: =+AW8*AW10/100 -> 0 | AX3: =+AX8*AX10/100 -> 0
B4: FECHA | C4: =TODAY() -> 45386 | H4: =+AF7 -> 163082 | I4: Calculado | J4: Medido | N4: =+AF8 -> 202642 | W4: Rec. | X4: =+W28+W27+U27+U28+S27+S28 -> 0 | AD4: Datos | AL4: Inventarios Proyectados al Cierre | AQ4: Calculado sap estadistico | AR4: Medido
H5: =+AG7 -> 0.6339236 | I5: =+AQ7 -> 391990.57 | J5: =+AR7 -> 391638.34 | N5: =+AG8 -> 0.63386388 | AA5: Ingreso datos | AD5: TMH Entrada | AE5: h% | AF5: TMS Ajustados | AG5: FeT% | AH5: Ajuste | AI5: TMH Ajustados | AL5: Inicial | AM5: Final cub. | AN5: delta | AO5: %h | AP5: Tms | AQ5: Tms | AR5: Tms
F6: Recepcion | H6: =+H4*H5 -> 103381.53 | J6: =+J5-I5 -> -352.22579 | N6: =+N4*N5 -> 128447.44 | Z6: =+AD6-AD7-AD9 -> -0.00011859919 | AA6: Recepcion (Ferronor + Camiones) | AD6: =Flujos!C4/(1-AE6) -> 392092.82 | AE6: =Flujos!R4 -> 0.0092167453 | AF6: =Flujos!G4 -> 388479 | AG6: =Flujos!H4 -> 0.6163158 | AI6: =+AF6/(1-AE6) -> 392092.82 | AK6: Preconcentrado | AL6: ='Datos Extra'!B38 -> 149936 | AM6: ='Datos Extra'!C38 -> 150934.6 | AN6: ='Datos Extra'!D38 -> 998.60122 | AO6: ='Datos Extra'!E38 -> 0.0096968122 | AP6: ='Datos Extra'!F38 -> 1453.9012 | AQ6: =+AL6*(1-AO6)+AF9-AF10 -> 145251.1 | AR6: =+AM6*(1-AO6) -> 149471.02
F7: =+AF6 -> 388479 | AA7: A Sinter Feed | AD7: =Flujos!C5/(1-AE7) -> 164651.14 | AE7: =Flujos!R5 -> 0.0095301 | AF7: =Flujos!G5 -> 163082 | AG7: =Flujos!H5 -> 0.6339236 | AI7: =+AF7/(1-AE7) -> 164651.14 | AK7: Sinter | AL7: ='Datos Extra'!B39 -> 435765 | AM7: ='Datos Extra'!C39 -> 395463 | AN7: ='Datos Extra'!D39 -> -40302 | AO7: ='Datos Extra'!E39 -> 0.0096713366 | AP7: ='Datos Extra'!F39 -> 149046.44 | AQ7: =+(AL7*(1-AO7)+AF7-AF8)+AF35+AF40+AF46 -> 391990.57 | AR7: =+AM7*(1-AO7) -> 391638.34
F8: =+AG6 -> 0.6163158 | R8: =+AF30 -> 0 | U8: =+AF35 -> 0 | W8: =+AF41 -> 0 | AA8: Embarque Sinter Feed | AD8: =Flujos!C6/(1-AE8) -> 204999.49 | AE8: =Flujos!R6 -> 0.0115 | AF8: =Flujos!G6 -> 202642 | AG8: =Flujos!H6 -> 0.63386388 | AI8: =+AF8/(1-AE8) -> 204999.49 | AK8: Silos | AL8: ='Datos Extra'!B40 -> 0 | AM8: ='Datos Extra'!C40 -> -2927.9472 | AN8: ='Datos Extra'!D40 -> -2927.9472 | AO8: ='Datos Extra'!E40 -> 0.0086 | AP8: ='Datos Extra'!F40 -> 8030.34
F9: =+F7*F8 -> 239425.75 | H9: =+AF9 -> 225397 | AA9: A Preconcentrado | AD9: =Flujos!C7/(1-AE9) -> 227441.68 | AE9: =Flujos!R7 -> 0.0089899 | AF9: =Flujos!G7 -> 225397 | AG9: =Flujos!H7 -> 0.603576 | AI9: =+AF9/(1-AE9) -> 227441.68 | AK9: TK Filtrado | AL9: ='Datos Extra'!B41 -> 0 | AM9: ='Datos Extra'!C41 -> -1980 | AN9: ='Datos Extra'!D41 -> -1980 | AO9: ='Datos Extra'!E41 -> 0 | AP9: ='Datos Extra'!F41 -> 2700
H10: =+AG9 -> 0.603576 | L10: =+AF34 -> 0 | M10: =+AD39 -> 0 | N10: =+AD45 -> 0 | AA10: Alim Silos Molienda | AD10: =Flujos!C8/(1-AE10) -> 230701.99 | AE10: =Flujos!R8 -> 0.0089899 | AF10: =Flujos!G8 -> 228628 | AG10: =Flujos!H8 -> 0.596871 | AI10: =+AF10/(1-AE10) -> 230701.99 | AK10: Pellet Feed | AL10: ='Datos Extra'!B42 -> 48104 | AM10: ='Datos Extra'!C42 -> 147374 | AN10: ='Datos Extra'!D42 -> 99270 | AO10: ='Datos Extra'!E42 -> 0.076449042 | AP10: ='Datos Extra'!F42 -> -350455.26 | AQ10: =+AL10*(1-AO10)+AF16+AF17-AF19 -> 132691.5 | AR10: =+AM10*(1-AO10) -> 136107.4
H11: =+H9*H10 -> 136044.22 | AA11: Delta Stock Silos Molienda | AD11: =Flujos!C9/(1-AE11) -> -2928.1824 | AE11: =Flujos!R9 -> 0.0086 | AF11: =Flujos!G9 -> -4354.5 | AG11: =Flujos!H9 -> 0.633045 | AI11: =+AF11/(1-AE11) -> -4392.2736 | AK11: Pila de emergencia | AL11: ='Datos Extra'!B43 -> 0 | AM11: ='Datos Extra'!C43 -> 0 | AN11: ='Datos Extra'!D43 -> 0 | AO11: ='Datos Extra'!E43 -> 0 | AP11: ='Datos Extra'!F43 -> 0 | AR11: =+AM11*(1-AO11) -> 0
AA12: Aliment Molienda Clasificación | AD12: =Flujos!C10/(1-AE12) -> 233303.1 | AE12: =Flujos!R10 -> 0.0076 | AF12: =Flujos!G10 -> 229834.02 | AG12: =Flujos!H10 -> 0.60589335 | AI12: =+AF12/(1-AE12) -> 231594.14 | AK12: Pellet Producto | AL12: ='Datos Extra'!B44 -> 65746 | AM12: ='Datos Extra'!C44 -> 14273.092 | AN12: ='Datos Extra'!D44 -> -51472.908 | AO12: ='Datos Extra'!E44 -> 0.005 | AP12: ='Datos Extra'!F44 -> -275163.14 | AQ12: =+AL12*(1-AO12)+P49-M52 -> 65417.27 | AR12: =+AM12*(1-AO12) -> 14201.727
R13: 0 | V13: =+AF36 -> 24345 | X13: =+AF42 -> 0 | AA13: DRF | AD13: =Flujos!C14/(1-AE13) -> 22756 | AE13: =Flujos!R14 -> 0 | AF13: =Flujos!G14 -> 20480.4 | AG13: =Flujos!H14 -> 0.105183 | AI13: =+AF13/(1-AE13) -> 20480.4 | AK13: Chips | AL13: ='Datos Extra'!B45 -> 24742 | AM13: ='Datos Extra'!C45 -> 12095.744 | AN13: ='Datos Extra'!D45 -> -12646.256 | AO13: ='Datos Extra'!E45 -> 0.005 | AP13: ='Datos Extra'!F45 -> -364.17 | AQ13: =+AL13*(1-AO13)+AF25 -> 24618.29 | AR13: =+AM13*(1-AO13) -> 12035.266
F14: Calculado | G14: Medido | AA14: Alimentación a TK Inventarios | AD14: =Flujos!C15/(1-AE14) -> 210873.17 | AE14: =Flujos!R15 -> 0.009954634 | AF14: =Flujos!G15 -> 208774 | AG14: =Flujos!H15 -> 0.66639 | AI14: =+AF14/(1-AE14) -> 210873.17 | AK14: Finos | AL14: ='Datos Extra'!B46 -> 2203 | AM14: ='Datos Extra'!C46 -> 1837.275 | AN14: ='Datos Extra'!D46 -> -365.72502 | AO14: ='Datos Extra'!E46 -> 0.035 | AP14: ='Datos Extra'!F46 -> 2125.4149 | AQ14: =+AL14*(1-AO14)-AF35 -> 2125.895 | AR14: =+AM14*(1-AO14) -> 1772.9704
E15: TMS | F15: =+(AL6*(1-AO6))+H9-G20 -> 145251.1 | G15: =+AR6 -> 149471.02 | S15: =+AF31 -> 9066.24 | Z15: =+AD15-J29 -> 230091.63 | AA15: Alimentación Filtrado | AD15: =Flujos!C16/(1-AE15) -> 230091.63 | AE15: =Flujos!R16 -> 0.083495571 | AF15: =Flujos!G16 -> 210880 | AG15: =Flujos!H16 -> 0.679635 | AI15: =+AF15/(1-AE15) -> 230091.63 | AK15: Derrames Molienda | AL15: ='Datos Extra'!B47 -> 0 | AM15: ='Datos Extra'!C47 -> 0 | AN15: ='Datos Extra'!D47 -> 0 | AO15: ='Datos Extra'!E47 -> 0 | AP15: ='Datos Extra'!F47 -> 0 | AR15: =+AM15*(1-AO15) -> 0
G16: =+G15-F15 -> 4219.918 | AA16: Pellet feed a Stock Final | AD16: =Flujos!C19/(1-AE16) -> 209647.65 | AE16: =Flujos!R19 -> 0.083495571 | AF16: =Flujos!G19 -> 192143 | AG16: =Flujos!H19 -> 0.6865 | AI16: =+AF16/(1-AE16) -> 209647.65
O17: Molienda | AA17: Pellet feed a Pila intermedia (camiones) | AD17: =Flujos!C20/(1-AE17) -> 0 | AE17: =Flujos!R20 -> 0.083495571 | AF17: =Flujos!G20 -> 0 | AG17: =Flujos!H20 -> 0.6865 | AI17: =+AF17/(1-AE17) -> 0 | AQ17: =+AQ10/(1-AO10) -> 143675.34
L18: tms | M18: finos | O18: RP | T18: =-S19+S15 -> 9066.24 | AA18: De filtros a Balling | AD18: =Flujos!C19/(1-AE18) -> 209647.65 | AE18: =Flujos!R21 -> 0.083495571 | AF18: =Flujos!G21 -> 15836.381 | AG18: =Flujos!H21 -> 0.720825 | AI18: =+AF18/(1-AE18) -> 17279.11 | AK18: Recepcion (FERRONOR + CAMIONES PRECONCE+ SINTER) | AN18: Recepcion (FERRONOR + CAMIONES PRECONCE+ SINTER) | AQ18: =+AQ17-M72 -> -3698.5268
K19: Entradas | L19: =+I25+H37+K35+O35 -> 227728.02 | M19: =+I27 -> 139254.91 | O19: =+(P49+R36+H46+H37)/I25 -> 0.82684451 | AA19: A embarque feed de Stock Pellet Feed | AD19: =Flujos!C20/(1-AE19) -> 0 | AE19: =Flujos!R22 -> 0.0788 | AF19: =Flujos!G22 -> 103878 | AG19: =Flujos!H22 -> 0.6868 | AI19: =+AF19/(1-AE19) -> 112763.79 | AK19: Pesometro | AL19: 812104 | AN19: SINTER | AQ19: =+AL10-L72 -> -2386
G20: =+AF10 -> 228628 | K20: Salidas | L20: =+D28+H46+P41 -> 212623.4 | M20: =+D30+H48+P51+R38+R45 -> 134060.36 | O20: RM | W20: =+X13-W28 -> 0 | X20: =+W28+W27 -> 0 | AA20: Aditivo a Balling + remolienda | AD20: =Flujos!C21/(1-AE20) -> 18736 | AE20: =Flujos!R23 -> 0 | AF20: =Flujos!G23 -> 0 | AG20: =Flujos!H23 -> 0 | AI20: =+AF20/(1-AE20) -> 0 | AK20: PI | AL20: =783793+13399 -> 797192 | AN20: PRECONCE
G21: =+AG10 -> 0.596871 | K21: Dif. Derrame | L21: =+L20-L19 -> -15104.624 | M21: =+M20-M19 -> -5194.5476 | O21: =+(P51+R38+H48+H38)/I27 -> 0.93684598 | V21: =+V13 -> 24345 | AA21: Pellet verde a endurecimiento | AD21: =Flujos!C22/(1-AE21) -> #DIV/0! | AE21: =Flujos!R24 -> 1 | AF21: =Flujos!G24 -> 0 | AG21: =Flujos!H24 -> 0 | AI21: =+AF21/(1-AE21) -> #DIV/0! | AK21: dif | AL21: =+AL19-AL20 -> 14912
G22: =+G20*G21 -> 136461.42 | I22: =Flujos!G9 -> -4354.5 | K22: Perd. Calado | L22: =AO40 -> -2878 | AA22: Chunk de endurecimiento a Pila Chunk | AD22: =Flujos!C23/(1-AE22) -> 0 | AE22: =Flujos!R25 -> 0 | AF22: =Flujos!G25 -> 0 | AG22: =Flujos!H25 -> 0 | AI22: =+AF22/(1-AE22) -> 0
I23: =Flujos!G9*Flujos!H9 -> -2756.5945 | K23: Dif. c/Ajustes | L23: =+L21-L22 -> -12226.624 | AA23: Aporte Oxidación Endurecimiento | AD23: =Flujos!C24/(1-AE23) -> 0 | AE23: =Flujos!R26 -> 0 | AF23: =Flujos!G26 -> 0 | AG23: =Flujos!H26 -> 0 | AI23: =+AF23/(1-AE23) -> 0 | AK23: A Silos
F24: =I25-D28-J29-I41 -> -1526.3763 | AA24: De endurecimiento a Harnero Producto | AD24: =Flujos!C25/(1-AE24) -> 0 | AE24: =Flujos!R27 -> 0 | AF24: =Flujos!G27 -> 0 | AG24: =Flujos!H27 -> 0 | AI24: =+AF24/(1-AE24) -> 0 | AK24: Pesometro | AL24: 612276 | AN24: =+AI15-AI16-AI17 -> 20443.982 | AP24: =+AL24+I73 -> 612276
I25: =Flujos!G10 -> 229834.02 | AA25: De harnero Producto a Pila Chip Fresco | AD25: =Flujos!C28/(1-AE25) -> 0 | AE25: =Flujos!R28 -> 0 | AF25: =Flujos!G28 -> 0 | AG25: =Flujos!H28 -> 0 | AI25: =+AF25/(1-AE25) -> 0 | AK25: PI | AL25: =587148 -> 587148 | AP25: =+AL25+I76 -> 587148
I26: =Flujos!H10 -> 0.60589335 | AA26: De Harnero Producto a Stock Pellets Básico | AD26: =Flujos!C29/(1-AE26) -> 0 | AE26: =Flujos!R29 -> 0 | AF26: =Flujos!G29 -> 0 | AG26: =Flujos!H29 -> 0 | AI26: =+AF26/(1-AE26) -> 0 | AK26: dif | AL26: =+AL24-AL25 -> 25128
I27: =I25*I26 -> 139254.91 | R27: A sinter | S27: =+AF34 -> 0 | U27: =+AF40 -> 0 | W27: =+AF45 -> 0 | AA27: Delta Stock Pellet Básico | AD27: =Flujos!C30/(1-AE27) -> -51473.367 | AE27: =Flujos!R30 -> 0.005 | AF27: =Flujos!G30 -> -35851.2 | AG27: =Flujos!H30 -> 0 | AI27: =+AF27/(1-AE27) -> -36031.357 | AN27: 474948
D28: =+AF13 -> 20480.4 | F28: =Flujos!G13 -> 21060.024 | J28: Derrames | K28: Derrame Cal. | R28: A Pellet Basico | S28: =+AF33 -> 0 | W28: =+AF44 -> 0 | AA28: Embarque Pellet Basico | AD28: =Flujos!C31/(1-AE28) -> 0 | AE28: =Flujos!R31 -> 0 | AF28: =Flujos!G31 -> 0 | AG28: =Flujos!H31 -> 0 | AI28: =+AF28/(1-AE28) -> 0 | AK28: Pellet Feed | AN28: 3826
D29: =+AG13 -> 0.105183 | F29: =Flujos!H13 -> 0.107445 | J29: =Flujos!G17 -> 0 | K29: =+I25-D28-H46-P41+K35+O35+H37+L22 -> 12226.624 | AA29: Planta de Harneo | AK29: Pesometro | AL29: 191229 | AN29: 264630
D30: =+D28*D29 -> 2154.1899 | F30: =F28*F29 -> 2262.7942 | J30: =Flujos!H17 -> 0.58 | AA30: A Pila Finos contaminados | AD30: ='Datos Extra'!B22 -> 0 | AE30: ='Datos Extra'!C22 -> 0.04 | AF30: ='Datos Extra'!D22 -> 0 | AG30: ='Datos Extra'!E22 -> 0.58 | AH30: ='Datos Extra'!F22 -> 0 | AI30: ='Datos Extra'!G22 -> 0 | AK30: PI | AL30: 198173 | AN30: 8225
J31: =+J29*J30 -> 0 | AA31: Alimentación Finos a Harneo | AD31: ='Datos Extra'!B23 -> 9444 | AE31: ='Datos Extra'!C23 -> 0.04 | AF31: ='Datos Extra'!D23 -> 9066.24 | AG31: ='Datos Extra'!E23 -> 0.58 | AH31: ='Datos Extra'!F23 -> 0 | AI31: ='Datos Extra'!G23 -> 0 | AK31: dif | AL31: =+AL29-AL30 -> -6944
AA32: Producto Harneo Finos Contaminados | AD32: ='Datos Extra'!B24 -> 2203 | AE32: ='Datos Extra'!C24 -> 0.028 | AF32: ='Datos Extra'!D24 -> 2141.316 | AG32: ='Datos Extra'!E24 -> 0.6256 | AH32: ='Datos Extra'!F24 -> 0 | AI32: ='Datos Extra'!G24 -> 0
E33: =Flujos!G12 -> 969.95 | I33: =Flujos!G15 -> 208774 | AA33: Producto Pila Finos a stock Pellet P. | AD33: ='Datos Extra'!B25 -> 0 | AE33: ='Datos Extra'!C25 -> 0 | AF33: ='Datos Extra'!D25 -> 0 | AG33: ='Datos Extra'!E25 -> 0 | AH33: ='Datos Extra'!F25 -> 0 | AI33: ='Datos Extra'!G25 -> 0 | AK33: Pellet Basico | AN33: RD | AO33: BASICO
E34: =Flujos!H12*Flujos!G12 -> 108.60433 | I34: =Flujos!H15 -> 0.66639 | AA34: Producto Pila Finos a stock Sinter | AD34: ='Datos Extra'!B26 -> 0 | AE34: ='Datos Extra'!C26 -> 0.026944684 | AF34: ='Datos Extra'!D26 -> 0 | AG34: ='Datos Extra'!E26 -> 0.62503473 | AH34: ='Datos Extra'!F26 -> 0 | AI34: ='Datos Extra'!G26 -> 0 | AK34: Pesometro | AL34: 278637 | AN34: 39050 | AO34: 253801
D35: Calculado | E35: Medido | I35: =I33*I34 -> 139124.91 | J35: DERRAME FILTRADO | K35: =+AF20 -> 0 | O35: =+AF23 -> 0 | AA35: A Pila Chips | AD35: ='Datos Extra'!B27 -> 0 | AE35: ='Datos Extra'!C27 -> 0 | AF35: ='Datos Extra'!D27 -> 0 | AG35: ='Datos Extra'!E27 -> 0 | AH35: ='Datos Extra'!F27 -> 0 | AI35: ='Datos Extra'!G27 -> 0 | AK35: PI | AL35: 272690 | AN35: 39050 | AO35: 254001
C36: TMS | D36: =+AQ10 -> 132691.5 | E36: =+AR10 -> 136107.4 | R36: =+AF25 -> 0 | AA36: Alimentación chip a Harneo | AD36: ='Datos Extra'!B28 -> 24345 | AE36: ='Datos Extra'!C28 -> 0 | AF36: ='Datos Extra'!D28 -> 24345 | AG36: ='Datos Extra'!E28 -> 0.65 | AH36: ='Datos Extra'!F28 -> 0 | AI36: ='Datos Extra'!G28 -> 0 | AK36: dif | AL36: =+AL34-AL35 -> 5947
E37: =+E36-D36 -> 3415.9036 | H37: =Flujos!G11 -> -2106 | Q37: =+M39+O35-P41 -> 0 | R37: =+AG25 -> 0 | V37: =Flujos!G38 -> 65670 | AA37: Producto Harneo Chips | AD37: ='Datos Extra'!B29 -> 24345 | AE37: ='Datos Extra'!C29 -> 0 | AF37: ='Datos Extra'!D29 -> 24345 | AG37: ='Datos Extra'!E29 -> 0.65 | AH37: ='Datos Extra'!F29 -> 0 | AI37: ='Datos Extra'!G29 -> 0
H38: =Flujos!G11*Flujos!H11 -> -1445.769 | Q38: =+M41-P43 -> 0 | R38: =+R36*R37 -> 0 | V38: =Flujos!H38 -> 0.65 | AA38: Producto Pila Chip a stock Pellet P. | AD38: ='Datos Extra'!B30 -> 0 | AE38: ='Datos Extra'!C30 -> 0 | AF38: ='Datos Extra'!D30 -> 0 | AG38: ='Datos Extra'!E30 -> 0 | AH38: ='Datos Extra'!F30 -> 0 | AI38: ='Datos Extra'!G30 -> 0
J39: =+AF18 -> 15836.381 | M39: =+AF21 -> 0 | V39: =V38*V37 -> 42685.5 | AA39: Producto Pila Chip a stock Sinter | AD39: ='Datos Extra'!B31 -> 0 | AE39: ='Datos Extra'!C31 -> 0 | AF39: ='Datos Extra'!D31 -> 0 | AG39: ='Datos Extra'!E31 -> 0 | AH39: ='Datos Extra'!F31 -> 0 | AI39: ='Datos Extra'!G31 -> 0 | AK39: Embarques | AM39: Pesometro | AN39: Calado | AP39: Fe | AQ39: humedad
F40: =+AF16 -> 192143 | J40: =+AG18 -> 0.720825 | M40: =+AG21 -> 0 | AA40: Producto Pila Chip a Embarque | AD40: ='Datos Extra'!B32 -> 0 | AE40: ='Datos Extra'!C32 -> 0 | AF40: ='Datos Extra'!D32 -> 0 | AG40: ='Datos Extra'!E32 -> 0 | AH40: ='Datos Extra'!F32 -> 0 | AI40: ='Datos Extra'!G32 -> 0 | AK40: Pellet Feed | AM40: =+SUM(AM41:AM44) -> 115642 | AN40: =+SUM(AN41:AN44) -> 112764 | AO40: =+AN40-AM40 -> -2878 | AP40: =IF(AN40=0,0,SUMPRODUCT(AN41:AN44,AP41:AP44)/AN40) -> 68.85 | AQ40: =IF(AN40=0,0,SUMPRODUCT(AN41:AN44,AQ41:AQ44)/AN40) -> 7.7
C41: =+AF19 -> 103878 | F41: =+AG16 -> 0.6865 | I41: =+AF15 -> 210880 | J41: =+M41 -> 0 | M41: =+M39*M40 -> 0 | P41: =+P49+R36+R43 -> 0 | AA41: A Pila Chunk | AD41: ='Datos Extra'!B33 -> 0 | AE41: ='Datos Extra'!C33 -> 0 | AF41: ='Datos Extra'!D33 -> 0 | AG41: ='Datos Extra'!E33 -> 0 | AH41: ='Datos Extra'!F33 -> 0 | AI41: ='Datos Extra'!G33 -> 0 | AK41: MN1 | AM41: ='Datos Extra'!C48 -> 115642 | AN41: ='Datos Extra'!D48 -> 112764 | AP41: ='Datos Extra'!F48 -> 68.85 | AQ41: ='Datos Extra'!G48 -> 7.7
C42: =+AG19 -> 0.6868 | F42: =+F40*F41 -> 131906.17 | I42: =+AG15 -> 0.679635 | P42: =+M41/P41 -> #DIV/0! | AA42: Alimentación Chunk a Harneo | AD42: ='Datos Extra'!B34 -> 0 | AE42: ='Datos Extra'!C34 -> 0 | AF42: ='Datos Extra'!D34 -> 0 | AG42: ='Datos Extra'!E34 -> 0 | AH42: ='Datos Extra'!F34 -> 0 | AI42: ='Datos Extra'!G34 -> 0 | AK42: MN2 | AM42: ='Datos Extra'!C49 -> 0 | AN42: ='Datos Extra'!D49 -> 0 | AP42: ='Datos Extra'!F49 -> 68.77 | AQ42: ='Datos Extra'!G49 -> 7.74
C43: =+C41*C42 -> 71343.41 | I43: =+I41*I42 -> 143321.43 | P43: =+R45+R38+P51 -> 0 | R43: =+AF41 -> 0 | AA43: Producto Harneo Chunk | AD43: ='Datos Extra'!B35 -> 0 | AE43: ='Datos Extra'!C35 -> 0 | AF43: ='Datos Extra'!D35 -> 0 | AG43: ='Datos Extra'!E35 -> 0 | AH43: ='Datos Extra'!F35 -> 0 | AI43: ='Datos Extra'!G35 -> 0 | AK43: MN3 | AM43: ='Datos Extra'!C50 -> 0 | AN43: ='Datos Extra'!D50 -> 0 | AP43: ='Datos Extra'!F50 -> 69.15 | AQ43: ='Datos Extra'!G50 -> 7.37
R44: =+AG22 -> 0 | S44: Chunk | AA44: Producto Pila Chank a stock Pellet P. | AD44: ='Datos Extra'!B36 -> 0 | AE44: ='Datos Extra'!C36 -> 0 | AF44: ='Datos Extra'!D36 -> 0 | AG44: ='Datos Extra'!E36 -> 0 | AH44: ='Datos Extra'!F36 -> 0 | AI44: ='Datos Extra'!G36 -> 0 | AK44: MN4 | AM44: ='Datos Extra'!C51 -> 0 | AN44: ='Datos Extra'!D51 -> 0 | AP44: ='Datos Extra'!F51 -> 69.15 | AQ44: ='Datos Extra'!G51 -> 7.37
G45: =+AF17 -> 0 | R45: =+R43*R44 -> 0 | AA45: Producto Pila Chank a stock Sinter | AD45: ='Datos Extra'!B37 -> 0 | AE45: ='Datos Extra'!C37 -> 0 | AF45: ='Datos Extra'!D37 -> 0 | AG45: ='Datos Extra'!E37 -> 0 | AH45: ='Datos Extra'!F37 -> 0 | AI45: ='Datos Extra'!G37 -> 0 | AK45: Pellet Producto | AM45: =+SUM(AM46:AM49) -> 0 | AN45: =+SUM(AN46:AN49) -> 0 | AO45: =+AN45-AM45 -> 0 | AP45: =+SUMPRODUCT(AN46:AN49,AP46:AP49)/AN45 -> #DIV/0! | AQ45: =+SUMPRODUCT(AN46:AN49,AQ46:AQ49)/AN45 -> #DIV/0!
G46: =+AG17 -> 0.6865 | H46: =+F40+G45 -> 192143 | AK46: MN1 | AM46: ='Datos Extra'!C52 -> 0 | AN46: ='Datos Extra'!D52 -> 0 | AP46: ='Datos Extra'!F52 -> 65.34 | AQ46: ='Datos Extra'!G52 -> 1.12
E47: =+G45 -> 0 | G47: =+G45*G46 -> 0 | H47: =+H48/H46 -> 0.6865 | AC47: Inventario Productos en Proceso | AK47: MN2 | AM47: ='Datos Extra'!C53 -> 0 | AN47: ='Datos Extra'!D53 -> 0 | AP47: ='Datos Extra'!F53 -> 65.18 | AQ47: ='Datos Extra'!G53 -> 0.69
E48: =+G46 -> 0.6865 | H48: =+F42+G47 -> 131906.17 | AC48: Inv. Inicial | AD48: Inv. Final | AE48: Delta | AF48: tms | AG48: Medido | AH48: Cubicado | AK48: MN3 | AM48: ='Datos Extra'!C54 -> 0 | AN48: ='Datos Extra'!D54 -> 0 | AP48: ='Datos Extra'!F54 -> 65.55 | AQ48: ='Datos Extra'!G54 -> 0.71
E49: =+E47*E48 -> 0 | P49: =+AF26 -> 0 | AA49: Finos para repaso | AC49: 36780 | AD49: 36848 | AE49: =+AD49-AC49 -> 68 | AF49: =+AE49*(1-AE31) -> 65.28 | AK49: MN4 | AM49: ='Datos Extra'!C55 -> 0 | AN49: ='Datos Extra'!D55 -> 0 | AP49: ='Datos Extra'!F55 -> 0 | AQ49: ='Datos Extra'!G55 -> 0
P50: =+AG26 -> 0 | AA50: Chunk fresco | AC50: 18126 | AD50: 21873 | AE50: =+AD50-AC50 -> 3747 | AF50: =+AE50*(1-AE35) -> 3747 | AG50: =+AC50+AF41-AF42 -> 18126 | AH50: =17644+2400-1290 -> 18754 | AK50: Sinter | AM50: =+SUM(AM51:AM54) -> 198872 | AN50: =+SUM(AN51:AN54) -> 204999 | AO50: =+AN50-AM50 -> 6127 | AP50: =+SUMPRODUCT(AN51:AN54,AP51:AP54)/AN50 -> 64.07 | AQ50: =+SUMPRODUCT(AN51:AN54,AQ51:AQ54)/AN50 -> 1.19
P51: =+P49*P50 -> 0 | AK51: MN1 | AM51: ='Datos Extra'!C56 -> 62770 | AN51: ='Datos Extra'!D56 -> 65510 | AP51: ='Datos Extra'!F56 -> 64.07 | AQ51: ='Datos Extra'!G56 -> 1.19
M52: =+AF28 -> 0 | R52: =+AF33 -> 0 | S52: =+AF38 -> 0 | T52: =+AF44 -> 0 | AK52: MN2 | AM52: ='Datos Extra'!C57 -> 136102 | AN52: ='Datos Extra'!D57 -> 139489 | AP52: ='Datos Extra'!F57 -> 64.07 | AQ52: ='Datos Extra'!G57 -> 1.19
M53: =+AG28 -> 0 | AK53: MN3 | AM53: ='Datos Extra'!C58 -> 0 | AN53: ='Datos Extra'!D58 -> 0 | AP53: ='Datos Extra'!F58 -> 0 | AQ53: ='Datos Extra'!G58 -> 0
M54: =+M52*M53 -> 0 | AK54: MN4 | AM54: ='Datos Extra'!C59 -> 0 | AN54: ='Datos Extra'!D59 -> 0 | AP54: ='Datos Extra'!F59 -> 0 | AQ54: ='Datos Extra'!G59 -> 0
AK55: Chip | AM55: =+SUM(AM56:AM57) -> 67282 | AN55: =+SUM(AN56:AN57) -> 66000 | AO55: =+AN55-AM55 -> -1282 | AP55: =+SUMPRODUCT(AN56:AN57,AP56:AP57)/AN55 -> 0 | AQ55: =+SUMPRODUCT(AN56:AN57,AQ56:AQ57)/AN55 -> 0
O56: Calculado | P56: Medido | AK56: MN1 | AM56: ='Datos Extra'!C60 -> 67282 | AN56: ='Datos Extra'!D60 -> 66000 | AP56: ='Datos Extra'!F60 -> 0 | AQ56: ='Datos Extra'!G60 -> 0
N57: TMS | O57: =+AQ12+R52+S52+T52 -> 65417.27 | P57: =+AR12 -> 14201.727 | AK57: MN2 | AM57: ='Datos Extra'!C61 -> 0 | AN57: ='Datos Extra'!D61 -> 0 | AP57: ='Datos Extra'!F61 -> 0 | AQ57: ='Datos Extra'!G61 -> 0
P58: =+P57-O57 -> -51215.543 | AM58: =AM55+AM50+AM45+AM40 -> 381796 | AN58: =AN56+AN50+AN45+AN40-AN43 -> 383763 | AO58: =+AN58-AM58 -> 1967
G68: Resumen TMH
B69: Datos Base | C69: ENTRADAS | E69: PRODUCCIÓN BALANCE | F69: EMBARQUE | G69: Entrada Proy. | H69: Traspasos | I69: Salidas Proy. | J69: Producción Mes | K69: Embarque Mes | L69: SAP INICIAL | M69: SAP FINAL | N69: Cubi. | O69: Dif. | P69: Costo | Q69: Existencia Contable
B70: =+AD26 -> 0 | C70: Pellets Básico | E70: =+AI26 -> 0 | F70: =+AI28 -> 0 | J70: =+E70+G70 -> 0 | K70: =+F70+I70 -> 0 | L70: ='Datos Extra'!B1 -> 66753 | M70: =+L70+J70-K70+H70 -> 66753 | N70: ='Datos Extra'!C44 -> 14273.092 | O70: =N70-M70 -> -52479.908 | P70: 97.84 | Q70: =+O70*P70 -> -5134634.2
B71: =+AD25 -> 0 | C71: Pellets Chips | E71: =+AI25 -> 0 | F71: =Flujos!G38/(1-Flujos!R38) -> 66000 | J71: =+E71+G71 -> 0 | K71: =+F71+I71 -> 66000 | L71: ='Datos Extra'!B2 -> 24736 | M71: =+L71+J71-K71+H71 -> -41264 | N71: ='Datos Extra'!C45 -> 12095.744 | O71: =N71-M71 -> 53359.744 | P71: 33.36538 | Q71: =+O71*P71 -> 1780368.1
B72: =+AD16+AD17 -> 209647.65 | C72: Pellets Feed | E72: =+AI16+AI17 -> 209647.65 | F72: =+AI19 -> 112763.79 | J72: =+E72+G72 -> 209647.65 | K72: =+F72+I72 -> 112763.79 | L72: ='Datos Extra'!B3 -> 50490 | M72: =+L72+J72-K72 -> 147373.86 | N72: ='Datos Extra'!C42 -> 147374 | O72: =N72-M72 -> 0.13602003 | P72: 43.87 | Q72: =+O72*P72 -> 5.9671987
B73: =+AD10 -> 230701.99 | C73: Alimentación Silos | E73: =+AI10 -> 230701.99 | F73: 0 | K73: =+E73+I73 -> 230701.99 | L73: ='Datos Extra'!B4 -> 0
C74: Concentrado | E74: =+AI15 -> 230091.63 | K74: =+E74/E73*K73 -> 230091.63 | L74: ='Datos Extra'!B5 -> 0
C75: Colas | E75: =+AI13 -> 20480.4 | K75: =+E75+G75 -> 20480.4 | L75: ='Datos Extra'!B6 -> 0
B76: =+AD9 -> 227441.68 | C76: Preconcentrado | E76: =+AI9 -> 227441.68 | I76: =I73 -> 0 | J76: =+E76+G76 -> 227441.68 | K76: =+E73+I76 -> 230701.99 | L76: ='Datos Extra'!B7 -> 150617 | M76: =+L76+J76-K76+H76 -> 147356.69 | N76: ='Datos Extra'!C38 -> 150934.6 | O76: =N76-M76 -> 3577.9111 | P76: 20.14 | Q76: =+O76*P76 -> 72059.129
B77: =+AD7 -> 164651.14 | C77: Sinter | E77: =+AI7 -> 164651.14 | F77: =+AI8 -> 204999.49 | H77: 0 | J77: =+E77+G77 -> 164651.14 | K77: =+F77+I77 -> 204999.49 | L77: ='Datos Extra'!B8 -> 435811 | M77: =+L77+J77-K77+AD34+H77 -> 395462.65 | N77: ='Datos Extra'!C39 -> 395463 | O77: =N77-M77 -> 0.35233619 | P77: 21.37 | Q77: =+O77*P77 -> 7.5294244
B78: =+AD33 -> 0 | C78: Finos Huasco | E78: =AD32 -> 2203 | F78: 0 | H78: 0 | J78: =+E78+G78 -> 2203 | K78: =+F78+I78 -> 0 | L78: ='Datos Extra'!B9 -> 2203 | M78: =J78+L78-K78+H78 -> 4406 | N78: ='Datos Extra'!C46 -> 1837.275 | O78: =N78-M78 -> -2568.725 | P78: 8.54854 | Q78: 0
C79: Granzas Cristales PP | E79: 0 | F79: 0 | J79: =+E79+G79 -> 0 | K79: =+F79+I79 -> 0 | L79: ='Datos Extra'!B10 -> 27 | M79: =+L79+E79-F79 -> 27 | N79: 0 | O79: =N79-M79 -> -27 | P79: 40.32 | Q79: =+O79*P79 -> -1088.64
C80: Granzas Cristales | E80: 0 | F80: 0 | J80: =+E80+G80 -> 0 | K80: =+F80+I80 -> 0 | L80: ='Datos Extra'!B11 -> 25122 | M80: =+L80+E80-F80 -> 25122 | N80: 0 | O80: =N80-M80 -> -25122 | P80: 29.61 | Q80: =+O80*P80 -> -743862.42
E81: =+E70+E71+E72+E77+E78 -> 376501.79 | F81: =+F70+F71+F72+F77+F78 -> 383763.28 | J81: =+J70+J71+J72+J77+J78 -> 376501.79 | K81: =+K70+K71+K72+K77+K78 -> 383763.28 | O81: =SUM(O70:O80) -> -23259.489 | Q81: =SUM(Q70:Q80) -> -4027144.5
K82: =+K81-K72 -> 270999.49 | O82: =SUM(O70:O80)-O76 -> -26837.4 | Q82: =SUM(Q70:Q80)-Q76 -> -4099203.6
E84: Alimentación | F84: RP | G84: Costo Fijo | H84: Costo Proceso M$USD
C85: Los Colorados
C86: Costo Mina | E86: ='Datos Extra'!B13 -> 841140 | F86: ='Datos Extra'!C13 -> 1 | G86: ='Datos Extra'!D13 -> 1.7937499 | H86: =+E86*G86 -> 1508794.8
C87: Costo Chancado | E87: ='Datos Extra'!B14 -> 799464 | F87: ='Datos Extra'!C14 -> 0.85 | G87: ='Datos Extra'!D14 -> 0.93275004 | H87: =+E87*G87 -> 745700.08
C88: Costo Planta Beneficio | E88: ='Datos Extra'!B15 -> 309440 | F88: ='Datos Extra'!C15 -> 0.15 | G88: ='Datos Extra'!D15 -> 1.1554859 | H88: =+E88*G88 -> 357553.55
C89: Costo Planta Rechazo | E89: ='Datos Extra'!B16 -> 719345 | F89: ='Datos Extra'!C16 -> 1 | G89: ='Datos Extra'!D16 -> 6.7708476 | H89: =+E89*G89 -> 4870575.3
C90: Costo Carguio Trenes | E90: ='Datos Extra'!B17 -> 0 | F90: ='Datos Extra'!C17 -> 0 | G90: ='Datos Extra'!D17 -> 12.734649 | H90: =+E90*G90 -> 0
G91: =SUM(G86:G90) -> 23.387482 | H91: =SUM(H86:H90) -> 7482623.7
C92: Planta Pellets
C93: Concentradora | E93: =+AF10/(1-AE10) -> 230701.99 | F93: =+#REF! -> #REF! | G93: ='Datos Extra'!D18 -> 20.331616 | H93: =+E93*G93 -> 4690544.3
C94: Pelletizacion | E94: =+AF18/(1-AE18) -> 17279.11 | F94: =+P49/J39 -> 0 | G94: ='Datos Extra'!D19 -> 8.2254775 | H94: =+E94*G94 -> 142128.93
C95: Staff | E95: =+AF26/(1-AE26)+AF25/(1-AE25)+AF17/(1-AE17)+AF16/(1-AE16) -> 209647.65 | F95: =+O19 -> 0.82684451 | G95: ='Datos Extra'!D20 -> 2.7579753 | H95: =+E95*G95 -> 578203.04
C96: Puerto | E96: =+E95 -> 209647.65 | F96: 1 | G96: ='Datos Extra'!D21 -> 2.7579753 | H96: =+E96*G96 -> 578203.04
G97: =SUM(G93:G96) -> 34.073045 | H97: =SUM(H93:H96) -> 5989079.3
G98: Costo Total | H98: =+H91+H97 -> 13471703
G99: Cash Cost | H99: =+H98/E96 -> 64.258784
